{"ranking":[{"url":"","count":12,"longCount":12,"retweet":990,"twit":"https://twitter.com/gen_senden/status/1074848777482235904","create_at":"2018-12-18T02:08:12Z","profile_image":"http://pbs.twimg.com/profile_images/1054454757652189184/SvKyOoJI_normal.jpg","image_urls":null,"videos":null,"urls":["https://twitter.com/i/web/status/1074848777482235904"]},{"url":"","count":7,"longCount":7,"retweet":980,"twit":"https://twitter.com/SplatoonJP/status/1074851116880297984","create_at":"2018-12-18T02:17:30Z","profile_image":"http://pbs.twimg.com/profile_images/819765217957552132/1WftJJM1_normal.jpg","image_urls":null,"videos":null,"urls":["https://support.nintendo.co.jp/app/answers/detail/a_id/34680"]},{"url":"","count":7,"longCount":7,"retweet":802,"twit":"https://twitter.com/akiko_lawson/status/1074854282870968320","create_at":"2018-12-18T02:30:05Z","profile_image":"http://pbs.twimg.com/profile_images/875517108884455426/q3HMm7hU_normal.jpg","image_urls":null,"videos":null,"urls":["http://lawson.eng.mg/7140a"]},{"url":"","count":12,"longCount":12,"retweet":773,"twit":"https://twitter.com/atarashiichizu/status/1074848941190000641","create_at":"2018-12-18T02:08:51Z","profile_image":"http://pbs.twimg.com/profile_images/910880514634006528/fk99YUka_normal.jpg","image_urls":null,"videos":null,"urls":["https://contents.atarashiichizu.com/?p=8627\u0026post_type=chizu_topic"]},{"url":"","count":2,"longCount":2,"retweet":570,"twit":"https://twitter.com/TDR_PR/status/1074856691701735425","create_at":"2018-12-18T02:39:39Z","profile_image":"http://pbs.twimg.com/profile_images/898027353032359937/9rmmKrb4_normal.jpg","image_urls":null,"videos":null,"urls":["https://twitter.com/i/web/status/1074856691701735425"]},{"url":"http://pbs.twimg.com/media/Duqpt03W4AAQHLI.jpg","count":7,"longCount":7,"retweet":520,"twit":"https://twitter.com/LoveLive_staff/status/1074858067446108160","create_at":"2018-12-18T02:45:07Z","profile_image":"http://pbs.twimg.com/profile_images/1027440922672259072/sHA_z7wD_normal.jpg","image_urls":["http://pbs.twimg.com/media/Duqpt03W4AAQHLI.jpg"],"videos":[{"aspect_ratio":[0,0],"duration_millis":0,"variants":null}],"urls":["http://ow.ly/WlvF30n1wkd"]},{"url":"http://pbs.twimg.com/media/DuqkjOpVsAAngNg.jpg","count":7,"longCount":7,"retweet":510,"twit":"https://twitter.com/RytoSle2/status/1074852390346547202","create_at":"2018-12-18T02:22:34Z","profile_image":"http://pbs.twimg.com/profile_images/1027376424074674176/69PiFZbk_normal.jpg","image_urls":["http://pbs.twimg.com/media/DuqkjOpVsAAngNg.jpg"],"videos":[{"aspect_ratio":[0,0],"duration_millis":0,"variants":null}],"urls":null},{"url":"http://pbs.twimg.com/media/DuqnjTXUcAAPgZQ.jpg","count":7,"longCount":7,"retweet":432,"twit":"https://twitter.com/kuroseP/status/1074855867743236096","create_at":"2018-12-18T02:36:23Z","profile_image":"http://pbs.twimg.com/profile_images/913044354326917120/7Ls5M1Sp_normal.jpg","image_urls":["http://pbs.twimg.com/media/DuqnjTXUcAAPgZQ.jpg"],"videos":[{"aspect_ratio":[0,0],"duration_millis":0,"variants":null}],"urls":null},{"url":"","count":7,"longCount":7,"retweet":419,"twit":"https://twitter.com/IdentityVJP/status/1074861811835514880","create_at":"2018-12-18T03:00:00Z","profile_image":"http://pbs.twimg.com/profile_images/1070869705383063552/pnce_YVX_normal.jpg","image_urls":null,"videos":null,"urls":["https://twitter.com/i/web/status/1074861811835514880"]},{"url":"http://pbs.twimg.com/media/Duqgc90V4AEPqP-.jpg","count":6,"longCount":6,"retweet":380,"twit":"https://twitter.com/kuroneko_1750/status/1074847886825775104","create_at":"2018-12-18T02:04:40Z","profile_image":"http://pbs.twimg.com/profile_images/1054602075064025088/u6L941S4_normal.jpg","image_urls":["http://pbs.twimg.com/media/Duqgc90V4AEPqP-.jpg"],"videos":[{"aspect_ratio":[0,0],"duration_millis":0,"variants":null}],"urls":null},{"url":"","count":2,"longCount":2,"retweet":375,"twit":"https://twitter.com/prompt_fmarinos/status/1074848186198441984","create_at":"2018-12-18T02:05:51Z","profile_image":"http://pbs.twimg.com/profile_images/813224924609294336/u3NGkJK8_normal.jpg","image_urls":null,"videos":null,"urls":["https://www.f-marinos.com/news/detail?id=5531","https://twitter.com/i/web/status/1074848186198441984"]},{"url":"","count":6,"longCount":6,"retweet":369,"twit":"https://twitter.com/yottan20001202/status/1074848600046284800","create_at":"2018-12-18T02:07:30Z","profile_image":"http://pbs.twimg.com/profile_images/1060401598839439360/3WWrr-MS_normal.jpg","image_urls":null,"videos":null,"urls":["https://twitter.com/i/web/status/1074848600046284800"]},{"url":"http://pbs.twimg.com/media/DuqiylUUUAAXrkW.jpg","count":2,"longCount":2,"retweet":348,"twit":"https://twitter.com/mentaro_1102/status/1074850459041423360","create_at":"2018-12-18T02:14:53Z","profile_image":"http://pbs.twimg.com/profile_images/978956641994399744/clLLzEBg_normal.jpg","image_urls":["http://pbs.twimg.com/media/DuqiylUUUAAXrkW.jpg"],"videos":[{"aspect_ratio":[0,0],"duration_millis":0,"variants":null}],"urls":null},{"url":"","count":5,"longCount":5,"retweet":314,"twit":"https://twitter.com/starvations/status/1074852414593748992","create_at":"2018-12-18T02:22:40Z","profile_image":"http://pbs.twimg.com/profile_images/875527828195823616/zuIdvyXC_normal.jpg","image_urls":null,"videos":null,"urls":["https://twitter.com/i/web/status/1074852414593748992"]},{"url":"http://pbs.twimg.com/media/DuqlOyAU8AAxarO.jpg","count":4,"longCount":4,"retweet":277,"twit":"https://twitter.com/okasanman/status/1074853419960098816","create_at":"2018-12-18T02:26:39Z","profile_image":"http://pbs.twimg.com/profile_images/629126808579878912/FFtYtsRZ_normal.jpg","image_urls":["http://pbs.twimg.com/media/DuqlOyAU8AAxarO.jpg","http://pbs.twimg.com/media/DuqlPgJU8AAwkF-.jpg"],"videos":[{"aspect_ratio":[0,0],"duration_millis":0,"variants":null},{"aspect_ratio":[0,0],"duration_millis":0,"variants":null}],"urls":["https://www.nbcnews.com/news/us-news/deer-poacher-sentenced-watch-bambi-every-month-during-year-missouri-n949051"]},{"url":"","count":7,"longCount":7,"retweet":271,"twit":"https://twitter.com/solids_info/status/1074859813656391680","create_at":"2018-12-18T02:52:04Z","profile_image":"http://pbs.twimg.com/profile_images/947837020251947009/F0IJdc5A_normal.jpg","image_urls":null,"videos":null,"urls":["https://twitter.com/i/web/status/1074859813656391680"]},{"url":"","count":3,"longCount":3,"retweet":248,"twit":"https://twitter.com/AKIBA_ICHI/status/1074848816212336641","create_at":"2018-12-18T02:08:22Z","profile_image":"http://pbs.twimg.com/profile_images/504473232838098945/_DKNRhmJ_normal.jpeg","image_urls":null,"videos":null,"urls":["https://twitter.com/i/web/status/1074848816212336641"]},{"url":"http://pbs.twimg.com/media/DuqfyOSU0AA6ELa.jpg","count":1,"longCount":1,"retweet":201,"twit":"https://twitter.com/kanihamiso/status/1074847221776928769","create_at":"2018-12-18T02:02:02Z","profile_image":"http://pbs.twimg.com/profile_images/412220691115544576/sCo2GEZX_normal.jpeg","image_urls":["http://pbs.twimg.com/media/DuqfyOSU0AA6ELa.jpg"],"videos":[{"aspect_ratio":[0,0],"duration_millis":0,"variants":null}],"urls":null},{"url":"","count":2,"longCount":2,"retweet":189,"twit":"https://twitter.com/usagi_anime/status/1074848543234351104","create_at":"2018-12-18T02:07:17Z","profile_image":"http://pbs.twimg.com/profile_images/1069969613205716994/nu3DojQv_normal.jpg","image_urls":null,"videos":null,"urls":["http://www.gochiusa.com/news/hp0001/index06730000.html"]},{"url":"http://pbs.twimg.com/media/Duqg2QDVsAAstla.jpg","count":3,"longCount":3,"retweet":188,"twit":"https://twitter.com/Manga_Materials/status/1074848450368364545","create_at":"2018-12-18T02:06:54Z","profile_image":"http://pbs.twimg.com/profile_images/1061122635059220481/_3604xc3_normal.jpg","image_urls":["http://pbs.twimg.com/media/Duqg2QDVsAAstla.jpg","http://pbs.twimg.com/media/Duqg2QFUwAAwrIF.jpg","http://pbs.twimg.com/media/Duqg2QGVsAAs_Qj.jpg","http://pbs.twimg.com/media/Duqg2QEU0AA4JaH.jpg"],"videos":[{"aspect_ratio":[0,0],"duration_millis":0,"variants":null},{"aspect_ratio":[0,0],"duration_millis":0,"variants":null},{"aspect_ratio":[0,0],"duration_millis":0,"variants":null},{"aspect_ratio":[0,0],"duration_millis":0,"variants":null}],"urls":["https://www.pixiv.net/fanbox/creator/16776564","https://www.pixiv.net/fanbox/creator/16776564/post/143872"]},{"url":"","count":2,"longCount":2,"retweet":182,"twit":"https://twitter.com/project_eevee/status/1074852009877127169","create_at":"2018-12-18T02:21:03Z","profile_image":"http://pbs.twimg.com/profile_images/1063064784009015296/DpBMY3Do_normal.jpg","image_urls":null,"videos":null,"urls":["https://twitter.com/i/web/status/1074852009877127169"]},{"url":"","count":1,"longCount":1,"retweet":182,"twit":"https://twitter.com/bunshun_online/status/1074847362009321473","create_at":"2018-12-18T02:02:35Z","profile_image":"http://pbs.twimg.com/profile_images/819843056471916545/g_R6HcQH_normal.jpg","image_urls":null,"videos":null,"urls":["http://bunshun.jp/articles/-/10053"]},{"url":"","count":5,"longCount":5,"retweet":175,"twit":"https://twitter.com/livedoornews/status/1074855194876207104","create_at":"2018-12-18T02:33:42Z","profile_image":"http://pbs.twimg.com/profile_images/875662964988166149/whdJTD2I_normal.jpg","image_urls":null,"videos":null,"urls":["http://news.livedoor.com/article/detail/15753316/"]},{"url":"","count":3,"longCount":3,"retweet":174,"twit":"https://twitter.com/livedoornews/status/1074859331286269962","create_at":"2018-12-18T02:50:09Z","profile_image":"http://pbs.twimg.com/profile_images/875662964988166149/whdJTD2I_normal.jpg","image_urls":null,"videos":null,"urls":["http://news.livedoor.com/article/detail/15755982/","https://twitter.com/i/web/status/1074859331286269962"]},{"url":"","count":2,"longCount":2,"retweet":140,"twit":"https://twitter.com/21s_ken/status/1074855922105647104","create_at":"2018-12-18T02:36:36Z","profile_image":"http://pbs.twimg.com/profile_images/1068718291751854080/0k0XCDlx_normal.jpg","image_urls":null,"videos":null,"urls":["https://ameblo.jp/2403isn/entry-12426705528.html"]},{"url":"http://pbs.twimg.com/media/DuqmKUxVsAAhUzS.jpg","count":1,"longCount":1,"retweet":134,"twit":"https://twitter.com/dekasugirumara/status/1074854485371973632","create_at":"2018-12-18T02:30:53Z","profile_image":"http://pbs.twimg.com/profile_images/947791096779640833/S-F5I1EM_normal.jpg","image_urls":["http://pbs.twimg.com/media/DuqmKUxVsAAhUzS.jpg"],"videos":[{"aspect_ratio":[0,0],"duration_millis":0,"variants":null}],"urls":null},{"url":"","count":1,"longCount":1,"retweet":126,"twit":"https://twitter.com/airimania/status/1074850201871908865","create_at":"2018-12-18T02:13:52Z","profile_image":"http://pbs.twimg.com/profile_images/947322595812061184/k4KoTghC_normal.jpg","image_urls":null,"videos":null,"urls":["https://twitter.com/i/web/status/1074850201871908865"]},{"url":"http://pbs.twimg.com/media/DuqjVD8U8AA0Zug.jpg","count":2,"longCount":2,"retweet":126,"twit":"https://twitter.com/rainmakerXokada/status/1074851051591761921","create_at":"2018-12-18T02:17:15Z","profile_image":"http://pbs.twimg.com/profile_images/995218207857258497/Jv41ScjM_normal.jpg","image_urls":["http://pbs.twimg.com/media/DuqjVD8U8AA0Zug.jpg"],"videos":[{"aspect_ratio":[0,0],"duration_millis":0,"variants":null}],"urls":null},{"url":"","count":3,"longCount":3,"retweet":116,"twit":"https://twitter.com/fm21wannuumui/status/1074855586481659906","create_at":"2018-12-18T02:35:16Z","profile_image":"http://pbs.twimg.com/profile_images/726764492609064961/K5fiop_9_normal.jpg","image_urls":null,"videos":null,"urls":["https://twitter.com/i/web/status/1074855586481659906"]},{"url":"","count":1,"longCount":1,"retweet":109,"twit":"https://twitter.com/UenoZooGardens/status/1074858105702309888","create_at":"2018-12-18T02:45:16Z","profile_image":"http://pbs.twimg.com/profile_images/877735101055946753/w1Q4GnSN_normal.jpg","image_urls":null,"videos":null,"urls":["http://UenoPandaLive.jp","https://twitter.com/i/web/status/1074858105702309888"]},{"url":"http://pbs.twimg.com/media/DuqiO1cUwAEuAPo.jpg","count":2,"longCount":2,"retweet":108,"twit":"https://twitter.com/coded4d9dc/status/1074849844009697280","create_at":"2018-12-18T02:12:27Z","profile_image":"http://pbs.twimg.com/profile_images/1010942634452398080/sqte4JVa_normal.jpg","image_urls":["http://pbs.twimg.com/media/DuqiO1cUwAEuAPo.jpg","http://pbs.twimg.com/media/DuqiO1eU0AEVfku.jpg","http://pbs.twimg.com/media/DuqiO1aU8AAp-v2.jpg","http://pbs.twimg.com/media/DuqiO1aUcAELGwo.jpg"],"videos":[{"aspect_ratio":[0,0],"duration_millis":0,"variants":null},{"aspect_ratio":[0,0],"duration_millis":0,"variants":null},{"aspect_ratio":[0,0],"duration_millis":0,"variants":null},{"aspect_ratio":[0,0],"duration_millis":0,"variants":null}],"urls":null},{"url":"http://pbs.twimg.com/media/DuqhOdPUUAALDZn.jpg","count":3,"longCount":3,"retweet":101,"twit":"https://twitter.com/coded4d9dc/status/1074848737703342081","create_at":"2018-12-18T02:08:03Z","profile_image":"http://pbs.twimg.com/profile_images/1010942634452398080/sqte4JVa_normal.jpg","image_urls":["http://pbs.twimg.com/media/DuqhOdPUUAALDZn.jpg","http://pbs.twimg.com/media/DuqhOdNUwAAR13G.jpg","http://pbs.twimg.com/media/DuqhOdPVAAAvxBC.jpg","http://pbs.twimg.com/media/DuqhOdOU8AARhyC.jpg"],"videos":[{"aspect_ratio":[0,0],"duration_millis":0,"variants":null},{"aspect_ratio":[0,0],"duration_millis":0,"variants":null},{"aspect_ratio":[0,0],"duration_millis":0,"variants":null},{"aspect_ratio":[0,0],"duration_millis":0,"variants":null}],"urls":null},{"url":"http://pbs.twimg.com/media/DuqlFMWU8AAu1x2.jpg","count":1,"longCount":1,"retweet":101,"twit":"https://twitter.com/solid_zonda/status/1074853453996802048","create_at":"2018-12-18T02:26:47Z","profile_image":"http://pbs.twimg.com/profile_images/899211651458650112/tuZSEvXF_normal.jpg","image_urls":["http://pbs.twimg.com/media/DuqlFMWU8AAu1x2.jpg","http://pbs.twimg.com/media/DuqlMH0UUAE8nLu.jpg","http://pbs.twimg.com/media/DuqlPK6VsAIfRKp.jpg"],"videos":[{"aspect_ratio":[0,0],"duration_millis":0,"variants":null},{"aspect_ratio":[0,0],"duration_millis":0,"variants":null},{"aspect_ratio":[0,0],"duration_millis":0,"variants":null}],"urls":null},{"url":"","count":3,"longCount":3,"retweet":97,"twit":"https://twitter.com/hiratapro/status/1074857633012568065","create_at":"2018-12-18T02:43:24Z","profile_image":"http://pbs.twimg.com/profile_images/2224996344/hplogo_normal.jpg","image_urls":null,"videos":null,"urls":["https://www.nhk-cul.co.jp/nhkcc-webapp/web_sp/WInformation.do?wbInformation.filePasu==/information/sp/school/8000/news/20181217_10114.html"]},{"url":"","count":1,"longCount":1,"retweet":91,"twit":"https://twitter.com/kabumatome/status/1074855186546405376","create_at":"2018-12-18T02:33:40Z","profile_image":"http://pbs.twimg.com/profile_images/473269954075062272/9DejMZcz_normal.png","image_urls":null,"videos":null,"urls":["http://kabumatome.doorblog.jp/archives/65932208.html"]},{"url":"","count":5,"longCount":5,"retweet":91,"twit":"https://twitter.com/Haagen_Dazs_JP/status/1074861812225499136","create_at":"2018-12-18T03:00:00Z","profile_image":"http://pbs.twimg.com/profile_images/756026452118601728/rjjsdSBb_normal.jpg","image_urls":null,"videos":null,"urls":["https://twitter.com/i/web/status/1074861812225499136"]},{"url":"http://pbs.twimg.com/media/Duqocl2U0AAZfd_.jpg","count":1,"longCount":1,"retweet":87,"twit":"https://twitter.com/natalie_mu/status/1074856675662675968","create_at":"2018-12-18T02:39:36Z","profile_image":"http://pbs.twimg.com/profile_images/541889848726921216/idvp5jki_normal.png","image_urls":["http://pbs.twimg.com/media/Duqocl2U0AAZfd_.jpg","http://pbs.twimg.com/media/Duqocy_VsAA03TV.jpg"],"videos":[{"aspect_ratio":[0,0],"duration_millis":0,"variants":null},{"aspect_ratio":[0,0],"duration_millis":0,"variants":null}],"urls":["https://natalie.mu/music/news/312645"]},{"url":"","count":2,"longCount":2,"retweet":85,"twit":"https://twitter.com/takarakuji_qoo/status/1074847185420742656","create_at":"2018-12-18T02:01:53Z","profile_image":"http://pbs.twimg.com/profile_images/1024582236551565312/Unz9_82b_normal.jpg","image_urls":null,"videos":null,"urls":["https://twitter.com/i/web/status/1074847185420742656"]},{"url":"http://pbs.twimg.com/media/DuqhqPeUYAAkye3.jpg","count":3,"longCount":3,"retweet":83,"twit":"https://twitter.com/coded4d9dc/status/1074849214968918016","create_at":"2018-12-18T02:09:57Z","profile_image":"http://pbs.twimg.com/profile_images/1010942634452398080/sqte4JVa_normal.jpg","image_urls":["http://pbs.twimg.com/media/DuqhqPeUYAAkye3.jpg","http://pbs.twimg.com/media/DuqhqPfVYAEsywj.jpg","http://pbs.twimg.com/media/DuqhqPpU0AAxOK_.jpg","http://pbs.twimg.com/media/DuqhqPwUcAA6pM6.jpg"],"videos":[{"aspect_ratio":[0,0],"duration_millis":0,"variants":null},{"aspect_ratio":[0,0],"duration_millis":0,"variants":null},{"aspect_ratio":[0,0],"duration_millis":0,"variants":null},{"aspect_ratio":[0,0],"duration_millis":0,"variants":null}],"urls":null},{"url":"http://pbs.twimg.com/media/DuqiNOsVYAEai64.jpg","count":2,"longCount":2,"retweet":81,"twit":"https://twitter.com/haruna__iikubo/status/1074849818185322496","create_at":"2018-12-18T02:12:21Z","profile_image":"http://pbs.twimg.com/profile_images/1074474767963439107/mxEGJ4FG_normal.jpg","image_urls":["http://pbs.twimg.com/media/DuqiNOsVYAEai64.jpg"],"videos":[{"aspect_ratio":[0,0],"duration_millis":0,"variants":null}],"urls":null},{"url":"http://pbs.twimg.com/media/Duqha49UYAAmecg.jpg","count":1,"longCount":1,"retweet":78,"twit":"https://twitter.com/coded4d9dc/status/1074848957979754496","create_at":"2018-12-18T02:08:55Z","profile_image":"http://pbs.twimg.com/profile_images/1010942634452398080/sqte4JVa_normal.jpg","image_urls":["http://pbs.twimg.com/media/Duqha49UYAAmecg.jpg","http://pbs.twimg.com/media/Duqha48UUAEeEWl.jpg","http://pbs.twimg.com/media/Duqha47UcAAGHfx.jpg","http://pbs.twimg.com/media/Duqha49U0AAbYgQ.jpg"],"videos":[{"aspect_ratio":[0,0],"duration_millis":0,"variants":null},{"aspect_ratio":[0,0],"duration_millis":0,"variants":null},{"aspect_ratio":[0,0],"duration_millis":0,"variants":null},{"aspect_ratio":[0,0],"duration_millis":0,"variants":null}],"urls":null},{"url":"","count":2,"longCount":2,"retweet":77,"twit":"https://twitter.com/ensemble_stars/status/1074861840453124096","create_at":"2018-12-18T03:00:07Z","profile_image":"http://pbs.twimg.com/profile_images/530523972790534144/d_bj9XQS_normal.png","image_urls":null,"videos":null,"urls":["https://twitter.com/i/web/status/1074861840453124096"]},{"url":"http://pbs.twimg.com/media/DuqighXUUAAjG8c.jpg","count":5,"longCount":5,"retweet":77,"twit":"https://twitter.com/phio_alchemist/status/1074850402305101824","create_at":"2018-12-18T02:14:40Z","profile_image":"http://pbs.twimg.com/profile_images/1058351597435015168/vlXheFZL_normal.jpg","image_urls":["http://pbs.twimg.com/media/DuqighXUUAAjG8c.jpg"],"videos":[{"aspect_ratio":[0,0],"duration_millis":0,"variants":null}],"urls":["https://www.vive.com/jp/year-end-vtuber/"]},{"url":"http://pbs.twimg.com/media/DuqnaQ2VsAAkBsT.jpg","count":2,"longCount":2,"retweet":76,"twit":"https://twitter.com/karapaia/status/1074855531888558080","create_at":"2018-12-18T02:35:03Z","profile_image":"http://pbs.twimg.com/profile_images/518269086954831872/oExhXCp9_normal.jpeg","image_urls":["http://pbs.twimg.com/media/DuqnaQ2VsAAkBsT.jpg"],"videos":[{"aspect_ratio":[0,0],"duration_millis":0,"variants":null}],"urls":["http://karapaia.com/archives/52268906.html?utm_source=twitter.com"]},{"url":"","count":2,"longCount":2,"retweet":74,"twit":"https://twitter.com/yukiyama0721/status/1074848185225338880","create_at":"2018-12-18T02:05:51Z","profile_image":"http://pbs.twimg.com/profile_images/1061773476409667586/wDTavS9f_normal.jpg","image_urls":null,"videos":null,"urls":["https://twitter.com/i/web/status/1074848185225338880"]},{"url":"","count":1,"longCount":1,"retweet":73,"twit":"https://twitter.com/Kstyle_news/status/1074851749293260808","create_at":"2018-12-18T02:20:01Z","profile_image":"http://pbs.twimg.com/profile_images/1690614906/twitter_profile_normal.png","image_urls":null,"videos":null,"urls":["http://www.kstyle-news.jp/article.ksn?articleNo=2107195"]},{"url":"http://pbs.twimg.com/media/DuqidtCU0AEuIvS.jpg","count":1,"longCount":1,"retweet":69,"twit":"https://twitter.com/coded4d9dc/status/1074850098863984640","create_at":"2018-12-18T02:13:27Z","profile_image":"http://pbs.twimg.com/profile_images/1010942634452398080/sqte4JVa_normal.jpg","image_urls":["http://pbs.twimg.com/media/DuqidtCU0AEuIvS.jpg","http://pbs.twimg.com/media/DuqidtAU8AAC0X_.jpg","http://pbs.twimg.com/media/DuqidtCUwAAcei5.jpg","http://pbs.twimg.com/media/DuqidtEUUAAQc2R.jpg"],"videos":[{"aspect_ratio":[0,0],"duration_millis":0,"variants":null},{"aspect_ratio":[0,0],"duration_millis":0,"variants":null},{"aspect_ratio":[0,0],"duration_millis":0,"variants":null},{"aspect_ratio":[0,0],"duration_millis":0,"variants":null}],"urls":null},{"url":"http://pbs.twimg.com/media/DuqlGyCU8AA2nup.jpg","count":1,"longCount":1,"retweet":69,"twit":"https://twitter.com/Kemura0/status/1074853003557916672","create_at":"2018-12-18T02:25:00Z","profile_image":"http://pbs.twimg.com/profile_images/1069250965075718144/j8u-WtOX_normal.jpg","image_urls":["http://pbs.twimg.com/media/DuqlGyCU8AA2nup.jpg"],"videos":[{"aspect_ratio":[0,0],"duration_millis":0,"variants":null}],"urls":null},{"url":"","count":2,"longCount":2,"retweet":66,"twit":"https://twitter.com/kyoukaraoreha_n/status/1074856556783529985","create_at":"2018-12-18T02:39:07Z","profile_image":"http://pbs.twimg.com/profile_images/1066701378792284160/hqvDrhvr_normal.jpg","image_urls":null,"videos":null,"urls":["https://twitter.com/kousai_shoko/status/1074694766695043072"]},{"url":"http://pbs.twimg.com/media/DuqoDlhVAAAwBHb.jpg","count":1,"longCount":1,"retweet":66,"twit":"https://twitter.com/dreamnara0324/status/1074856249735360512","create_at":"2018-12-18T02:37:54Z","profile_image":"http://pbs.twimg.com/profile_images/1073175139687092224/k9dsXfzL_normal.jpg","image_urls":["http://pbs.twimg.com/media/DuqoDlhVAAAwBHb.jpg"],"videos":[{"aspect_ratio":[0,0],"duration_millis":0,"variants":null}],"urls":null},{"url":"","count":2,"longCount":2,"retweet":66,"twit":"https://twitter.com/jworldtokyo/status/1074847473984667648","create_at":"2018-12-18T02:03:02Z","profile_image":"http://pbs.twimg.com/profile_images/875563221767172096/uaz3T_Z9_normal.jpg","image_urls":null,"videos":null,"urls":["https://twitter.com/i/web/status/1074847473984667648"]},{"url":"http://pbs.twimg.com/media/Duqg6yqVYAIz5ma.jpg","count":1,"longCount":1,"retweet":65,"twit":"https://twitter.com/itm_nlab/status/1074849450613399554","create_at":"2018-12-18T02:10:53Z","profile_image":"http://pbs.twimg.com/profile_images/875585661222273024/__F5GwAW_normal.jpg","image_urls":["http://pbs.twimg.com/media/Duqg6yqVYAIz5ma.jpg"],"videos":[{"aspect_ratio":[0,0],"duration_millis":0,"variants":null}],"urls":["http://nlab.itmedia.co.jp/nl/articles/1812/18/news071.html"]},{"url":"","count":1,"longCount":1,"retweet":63,"twit":"https://twitter.com/wni_jp/status/1074851733405196288","create_at":"2018-12-18T02:19:57Z","profile_image":"http://pbs.twimg.com/profile_images/878447388641251328/ZAeYiaAF_normal.jpg","image_urls":null,"videos":null,"urls":["https://weathernews.jp/s/topics/201812/180065/"]},{"url":"","count":2,"longCount":2,"retweet":63,"twit":"https://twitter.com/marginal4_anime/status/1074855625127976961","create_at":"2018-12-18T02:35:25Z","profile_image":"http://pbs.twimg.com/profile_images/761509007617986561/vJUeIAAd_normal.jpg","image_urls":null,"videos":null,"urls":["https://twitter.com/i/web/status/1074855625127976961"]},{"url":"http://pbs.twimg.com/media/DuqkTOYVAAEyyM3.jpg","count":3,"longCount":3,"retweet":63,"twit":"https://twitter.com/Trainfo_ALERT/status/1074852117578272769","create_at":"2018-12-18T02:21:29Z","profile_image":"http://pbs.twimg.com/profile_images/875485038296551424/UawM8e9w_normal.jpg","image_urls":["http://pbs.twimg.com/media/DuqkTOYVAAEyyM3.jpg"],"videos":[{"aspect_ratio":[0,0],"duration_millis":0,"variants":null}],"urls":null},{"url":"","count":1,"longCount":1,"retweet":60,"twit":"https://twitter.com/aotetsu_news/status/1074849269264277506","create_at":"2018-12-18T02:10:10Z","profile_image":"http://pbs.twimg.com/profile_images/1132940246/__________normal.jpg","image_urls":null,"videos":null,"urls":["https://twitter.com/i/web/status/1074849269264277506"]},{"url":"","count":1,"longCount":1,"retweet":59,"twit":"https://twitter.com/KinbakuTw/status/1074852126994493441","create_at":"2018-12-18T02:21:31Z","profile_image":"http://pbs.twimg.com/profile_images/915440045288329216/PDZtA_-c_normal.jpg","image_urls":null,"videos":null,"urls":["https://twitter.com/i/web/status/1074852126994493441"]},{"url":"http://pbs.twimg.com/media/DuqmSD4UYAE5nSZ.jpg","count":1,"longCount":1,"retweet":59,"twit":"https://twitter.com/fashionpressnet/status/1074854292547198977","create_at":"2018-12-18T02:30:07Z","profile_image":"http://pbs.twimg.com/profile_images/890882778878758913/U37FSz9D_normal.jpg","image_urls":["http://pbs.twimg.com/media/DuqmSD4UYAE5nSZ.jpg"],"videos":[{"aspect_ratio":[0,0],"duration_millis":0,"variants":null}],"urls":["https://www.fashion-press.net/news/45564"]},{"url":"","count":1,"longCount":1,"retweet":59,"twit":"https://twitter.com/tarts_HIROBATO/status/1074852225850105856","create_at":"2018-12-18T02:21:55Z","profile_image":"http://pbs.twimg.com/profile_images/984372330989207553/-0LSYVnT_normal.jpg","image_urls":null,"videos":null,"urls":["https://twitter.com/i/web/status/1074852225850105856"]},{"url":"http://pbs.twimg.com/media/DuqhrB2VAAAJ5LB.jpg","count":2,"longCount":2,"retweet":58,"twit":"https://twitter.com/hjsakusen/status/1074849796064632832","create_at":"2018-12-18T02:12:15Z","profile_image":"http://pbs.twimg.com/profile_images/719495786338209792/CqWdAAEa_normal.jpg","image_urls":["http://pbs.twimg.com/media/DuqhrB2VAAAJ5LB.jpg","http://pbs.twimg.com/media/DuqhspdVYAEzLTC.jpg","http://pbs.twimg.com/media/DuqhuUPU8AARqTp.jpg"],"videos":[{"aspect_ratio":[0,0],"duration_millis":0,"variants":null},{"aspect_ratio":[0,0],"duration_millis":0,"variants":null},{"aspect_ratio":[0,0],"duration_millis":0,"variants":null}],"urls":null},{"url":"","count":1,"longCount":1,"retweet":58,"twit":"https://twitter.com/Ponta/status/1074861812003160064","create_at":"2018-12-18T03:00:00Z","profile_image":"http://pbs.twimg.com/profile_images/1069391918562299905/N7KJBkkE_normal.jpg","image_urls":null,"videos":null,"urls":["https://twitter.com/i/web/status/1074861812003160064"]},{"url":"","count":2,"longCount":2,"retweet":57,"twit":"https://twitter.com/mizunoyoshiki/status/1074855420282384385","create_at":"2018-12-18T02:34:36Z","profile_image":"http://pbs.twimg.com/profile_images/1058127357641281536/Czez2Rr__normal.jpg","image_urls":null,"videos":null,"urls":["https://twitter.com/news_line_me/status/1074846900270952448"]},{"url":"","count":2,"longCount":2,"retweet":57,"twit":"https://twitter.com/nhk_news/status/1074850239792611328","create_at":"2018-12-18T02:14:01Z","profile_image":"http://pbs.twimg.com/profile_images/712261429701713920/mkdC8tNc_normal.jpg","image_urls":null,"videos":null,"urls":["https://www3.nhk.or.jp/news/html/20181218/k10011750871000.html"]},{"url":"","count":1,"longCount":1,"retweet":56,"twit":"https://twitter.com/TVXQ_INFO_/status/1074850732828815360","create_at":"2018-12-18T02:15:59Z","profile_image":"http://pbs.twimg.com/profile_images/975781973422522376/9yPx0BUM_normal.jpg","image_urls":null,"videos":null,"urls":["https://twitter.com/i/web/status/1074850732828815360"]},{"url":"","count":1,"longCount":1,"retweet":50,"twit":"https://twitter.com/EFF/status/1074850628977909760","create_at":"2018-12-18T02:15:34Z","profile_image":"http://pbs.twimg.com/profile_images/1022932965892939776/aJgE2T5l_normal.jpg","image_urls":null,"videos":null,"urls":["https://www.eff.org/deeplinks/2018/12/dear-tumblr-banning-adult-content-wont-make-your-site-better-it-will-harm-sex"]},{"url":"","count":2,"longCount":2,"retweet":50,"twit":"https://twitter.com/Sankei_news/status/1074856090636976128","create_at":"2018-12-18T02:37:16Z","profile_image":"http://pbs.twimg.com/profile_images/1051598198756630528/8a4rUyDd_normal.jpg","image_urls":null,"videos":null,"urls":["https://www.sankei.com/affairs/news/181218/afr1812180008-n1.html"]},{"url":"","count":2,"longCount":2,"retweet":49,"twit":"https://twitter.com/AUTOMATONJapan/status/1074860518886658048","create_at":"2018-12-18T02:54:52Z","profile_image":"http://pbs.twimg.com/profile_images/496898252017393666/djSiHQOx_normal.jpeg","image_urls":null,"videos":null,"urls":["https://automaton-media.com/articles/newsjp/20181218-81788/"]},{"url":"","count":1,"longCount":1,"retweet":48,"twit":"https://twitter.com/WebMoney_INFO/status/1074847438404370432","create_at":"2018-12-18T02:02:53Z","profile_image":"http://pbs.twimg.com/profile_images/1057797326507364352/Yg7myFyP_normal.jpg","image_urls":null,"videos":null,"urls":["https://twitter.com/i/web/status/1074847438404370432"]},{"url":"http://pbs.twimg.com/media/DuqgK0kVYAEwnFw.jpg","count":2,"longCount":2,"retweet":46,"twit":"https://twitter.com/SugarNSpice0610/status/1074847579077144576","create_at":"2018-12-18T02:03:27Z","profile_image":"http://pbs.twimg.com/profile_images/1066501112709111808/8jjtas6a_normal.jpg","image_urls":["http://pbs.twimg.com/media/DuqgK0kVYAEwnFw.jpg","http://pbs.twimg.com/media/DuqgK0lVYAAVNA-.jpg"],"videos":[{"aspect_ratio":[0,0],"duration_millis":0,"variants":null},{"aspect_ratio":[0,0],"duration_millis":0,"variants":null}],"urls":null},{"url":"","count":4,"longCount":4,"retweet":46,"twit":"https://twitter.com/kotobukiya_npb/status/1074849320279584769","create_at":"2018-12-18T02:10:22Z","profile_image":"http://pbs.twimg.com/profile_images/879883439817637888/A3l_Fmv1_normal.jpg","image_urls":null,"videos":null,"urls":["https://twitter.com/i/web/status/1074849320279584769"]},{"url":"http://pbs.twimg.com/media/Duqgkh5U0AEMmxu.jpg","count":2,"longCount":2,"retweet":43,"twit":"https://twitter.com/miinyan73/status/1074848015901290497","create_at":"2018-12-18T02:05:11Z","profile_image":"http://pbs.twimg.com/profile_images/1035384609859547136/hVNoWjql_normal.jpg","image_urls":["http://pbs.twimg.com/media/Duqgkh5U0AEMmxu.jpg"],"videos":[{"aspect_ratio":[0,0],"duration_millis":0,"variants":null}],"urls":null},{"url":"","count":1,"longCount":1,"retweet":43,"twit":"https://twitter.com/haruna__iikubo/status/1074847667736391680","create_at":"2018-12-18T02:03:48Z","profile_image":"http://pbs.twimg.com/profile_images/1074474767963439107/mxEGJ4FG_normal.jpg","image_urls":null,"videos":null,"urls":["https://twitter.com/worldjapan/status/1074841880829976578"]},{"url":"http://pbs.twimg.com/media/DuqhCbkU8AAzEpO.jpg","count":1,"longCount":1,"retweet":39,"twit":"https://twitter.com/kano_2525/status/1074848529007300608","create_at":"2018-12-18T02:07:13Z","profile_image":"http://pbs.twimg.com/profile_images/1067655506100011013/Wo2mBSeh_normal.jpg","image_urls":["http://pbs.twimg.com/media/DuqhCbkU8AAzEpO.jpg"],"videos":[{"aspect_ratio":[0,0],"duration_millis":0,"variants":null}],"urls":null},{"url":"http://pbs.twimg.com/media/DuQlB1wU0AAUElX.jpg","count":1,"longCount":1,"retweet":39,"twit":"https://twitter.com/cupnoodle_jp/status/1074854261664686080","create_at":"2018-12-18T02:30:00Z","profile_image":"http://pbs.twimg.com/profile_images/604091541892694016/KKAI5OpD_normal.jpg","image_urls":["http://pbs.twimg.com/media/DuQlB1wU0AAUElX.jpg"],"videos":[{"aspect_ratio":[0,0],"duration_millis":0,"variants":null}],"urls":null},{"url":"","count":2,"longCount":2,"retweet":39,"twit":"https://twitter.com/tokyonecro_sm/status/1074850528868237313","create_at":"2018-12-18T02:15:10Z","profile_image":"http://pbs.twimg.com/profile_images/1046667176508252161/0k2SyZzH_normal.jpg","image_urls":null,"videos":null,"urls":["http://pc-play.games.dmm.com/play/necro_suicide_mission/","https://twitter.com/i/web/status/1074850528868237313"]},{"url":"http://pbs.twimg.com/media/DuqpabOVAAAV3Np.jpg","count":1,"longCount":1,"retweet":39,"twit":"https://twitter.com/kingjim/status/1074857738931363840","create_at":"2018-12-18T02:43:49Z","profile_image":"http://pbs.twimg.com/profile_images/1057646495472607232/NU_dU2UA_normal.jpg","image_urls":["http://pbs.twimg.com/media/DuqpabOVAAAV3Np.jpg"],"videos":[{"aspect_ratio":[0,0],"duration_millis":0,"variants":null}],"urls":null},{"url":"","count":1,"longCount":1,"retweet":39,"twit":"https://twitter.com/pps_as/status/1074854623800750080","create_at":"2018-12-18T02:31:26Z","profile_image":"http://pbs.twimg.com/profile_images/980456414337363969/W-ItN049_normal.jpg","image_urls":null,"videos":null,"urls":["https://twitter.com/i/web/status/1074854623800750080"]},{"url":"","count":1,"longCount":1,"retweet":38,"twit":"https://twitter.com/YahooNewsTopics/status/1074850805180559360","create_at":"2018-12-18T02:16:16Z","profile_image":"http://pbs.twimg.com/profile_images/875506779743895552/jqN_tEe4_normal.jpg","image_urls":null,"videos":null,"urls":["https://yahoo.jp/638w5A"]},{"url":"","count":2,"longCount":2,"retweet":37,"twit":"https://twitter.com/DHCNetTV/status/1074848342423662592","create_at":"2018-12-18T02:06:29Z","profile_image":"http://pbs.twimg.com/profile_images/848693833789448192/6sefFCNH_normal.jpg","image_urls":null,"videos":null,"urls":["https://dhctv.jp/movie/102022/"]},{"url":"","count":3,"longCount":3,"retweet":37,"twit":"https://twitter.com/FTDM_official/status/1074852185551167488","create_at":"2018-12-18T02:21:45Z","profile_image":"http://pbs.twimg.com/profile_images/1024524049467101185/WLLAWUms_normal.jpg","image_urls":null,"videos":null,"urls":["https://twitter.com/i/web/status/1074852185551167488"]},{"url":"","count":1,"longCount":1,"retweet":36,"twit":"https://twitter.com/wanpakutenshi/status/1074849014497955840","create_at":"2018-12-18T02:09:09Z","profile_image":"http://pbs.twimg.com/profile_images/863775670484189184/RZJt6Tg4_normal.jpg","image_urls":null,"videos":null,"urls":["https://twitter.com/i/web/status/1074849014497955840"]},{"url":"","count":1,"longCount":1,"retweet":35,"twit":"https://twitter.com/afpbbcom/status/1074855522657017856","create_at":"2018-12-18T02:35:01Z","profile_image":"http://pbs.twimg.com/profile_images/557115603169726464/oJ8VVNus_normal.png","image_urls":null,"videos":null,"urls":["http://www.afpbb.com/articles/-/3202631"]},{"url":"http://pbs.twimg.com/media/DuqgJJYVsAAu-0a.jpg","count":2,"longCount":2,"retweet":35,"twit":"https://twitter.com/yottan20001202/status/1074847562539065344","create_at":"2018-12-18T02:03:23Z","profile_image":"http://pbs.twimg.com/profile_images/1060401598839439360/3WWrr-MS_normal.jpg","image_urls":["http://pbs.twimg.com/media/DuqgJJYVsAAu-0a.jpg","http://pbs.twimg.com/media/DuqgJJYUYAE5UER.jpg"],"videos":[{"aspect_ratio":[0,0],"duration_millis":0,"variants":null},{"aspect_ratio":[0,0],"duration_millis":0,"variants":null}],"urls":null},{"url":"","count":1,"longCount":1,"retweet":35,"twit":"https://twitter.com/ishiitakaaki/status/1074848081844137984","create_at":"2018-12-18T02:05:27Z","profile_image":"http://pbs.twimg.com/profile_images/1654603221/ishii_takaaki______normal.jpg","image_urls":null,"videos":null,"urls":["https://www.youtube.com/watch?v=xFoNoGtJq1E\u0026t=2620s","http://blog.livedoor.jp/ishiitakaaki3/archives/10940120.html"]},{"url":"","count":2,"longCount":2,"retweet":31,"twit":"https://twitter.com/Computerozi/status/1074861667358396416","create_at":"2018-12-18T02:59:26Z","profile_image":"http://pbs.twimg.com/profile_images/1029876307113336833/T2PneL8g_normal.jpg","image_urls":null,"videos":null,"urls":["https://www.amazon.co.jp/dp/409128826X/ref=cm_sw_r_tw_dp_U_x_NjggCbE9BNF9C"]},{"url":"http://pbs.twimg.com/ext_tw_video_thumb/1074850505736839168/pu/img/bvCJCCNnJeia_w2o.jpg","count":1,"longCount":1,"retweet":30,"twit":"https://twitter.com/bunbunhatiga/status/1074850634657083392","create_at":"2018-12-18T02:15:35Z","profile_image":"http://pbs.twimg.com/profile_images/755287660336340992/9C1fBMtx_normal.jpg","image_urls":["http://pbs.twimg.com/ext_tw_video_thumb/1074850505736839168/pu/img/bvCJCCNnJeia_w2o.jpg"],"videos":[{"aspect_ratio":[16,9],"duration_millis":138672,"variants":[{"content_type":"video/mp4","bitrate":832000,"url":"https://video.twimg.com/ext_tw_video/1074850505736839168/pu/vid/640x360/MGPJL9JkiTD6CR1x.mp4?tag=6"},{"content_type":"application/x-mpegURL","bitrate":0,"url":"https://video.twimg.com/ext_tw_video/1074850505736839168/pu/pl/3LIElDM7qdTjiH2k.m3u8?tag=6"},{"content_type":"video/mp4","bitrate":256000,"url":"https://video.twimg.com/ext_tw_video/1074850505736839168/pu/vid/320x180/FU9BP4Wy7JtuGuM5.mp4?tag=6"}]}],"urls":null},{"url":"","count":1,"longCount":1,"retweet":30,"twit":"https://twitter.com/ona_monkey_1/status/1074852847726907392","create_at":"2018-12-18T02:24:23Z","profile_image":"http://pbs.twimg.com/profile_images/1072884426344787968/KN0uLNuT_normal.jpg","image_urls":null,"videos":null,"urls":["https://twitter.com/i/web/status/1074852847726907392"]},{"url":"","count":1,"longCount":1,"retweet":30,"twit":"https://twitter.com/nikkei/status/1074848852895780865","create_at":"2018-12-18T02:08:30Z","profile_image":"http://pbs.twimg.com/profile_images/926053940449263616/1I1Q_Plx_normal.jpg","image_urls":null,"videos":null,"urls":["https://twitter.com/i/web/status/1074848852895780865"]},{"url":"http://pbs.twimg.com/media/DuqqQMsUwAARtvZ.jpg","count":1,"longCount":1,"retweet":29,"twit":"https://twitter.com/Trainfo_/status/1074858661829201920","create_at":"2018-12-18T02:47:29Z","profile_image":"http://pbs.twimg.com/profile_images/894528095167717382/Ep6P0-vj_normal.jpg","image_urls":["http://pbs.twimg.com/media/DuqqQMsUwAARtvZ.jpg"],"videos":[{"aspect_ratio":[0,0],"duration_millis":0,"variants":null}],"urls":null},{"url":"","count":1,"longCount":1,"retweet":29,"twit":"https://twitter.com/kijima2167/status/1074851903614271488","create_at":"2018-12-18T02:20:38Z","profile_image":"http://pbs.twimg.com/profile_images/1024832376508051456/cjEFXMz-_normal.jpg","image_urls":null,"videos":null,"urls":["https://twitter.com/i/web/status/1074851903614271488"]},{"url":"","count":1,"longCount":1,"retweet":29,"twit":"https://twitter.com/smith796000/status/1074861098812071936","create_at":"2018-12-18T02:57:10Z","profile_image":"http://pbs.twimg.com/profile_images/1516936478/twitter_normal.JPG","image_urls":null,"videos":null,"urls":["https://weekly-economist.mainichi.jp/articles/20181225/se1/00m/020/068000c?fbclid=IwAR0H0dxxmWRt44BtbBVKzV0bdvlC52CaYAc4nxcHjqoXp39OQYo-aoPiYbw"]},{"url":"http://pbs.twimg.com/media/DuqiEnxU8AEZ0hr.jpg","count":1,"longCount":1,"retweet":28,"twit":"https://twitter.com/kingilliya/status/1074849667370733568","create_at":"2018-12-18T02:11:45Z","profile_image":"http://pbs.twimg.com/profile_images/932624947620462592/XklBsg4Q_normal.jpg","image_urls":["http://pbs.twimg.com/media/DuqiEnxU8AEZ0hr.jpg"],"videos":[{"aspect_ratio":[0,0],"duration_millis":0,"variants":null}],"urls":null},{"url":"http://pbs.twimg.com/media/DuqidX2U8AAOxhj.jpg","count":1,"longCount":1,"retweet":28,"twit":"https://twitter.com/enmi_g/status/1074850094770401282","create_at":"2018-12-18T02:13:26Z","profile_image":"http://pbs.twimg.com/profile_images/1059870385334759424/9lRjwb7x_normal.jpg","image_urls":["http://pbs.twimg.com/media/DuqidX2U8AAOxhj.jpg"],"videos":[{"aspect_ratio":[0,0],"duration_millis":0,"variants":null}],"urls":["https://hochi.news/amp/baseball/mlb/20181218-OHT1T50044.html?from=rss\u0026utm_source=dlvr.it\u0026utm_medium=twitter\u0026__twitter_impression=true"]},{"url":"","count":1,"longCount":1,"retweet":23,"twit":"https://twitter.com/Shim_Ls2v2/status/1074855520626855936","create_at":"2018-12-18T02:35:00Z","profile_image":"http://pbs.twimg.com/profile_images/1047066870493405187/lLLLLdKx_normal.jpg","image_urls":null,"videos":null,"urls":["https://twitter.com/i/web/status/1074855520626855936"]},{"url":"http://pbs.twimg.com/media/DuqkbLBUUAA8LcR.jpg","count":1,"longCount":1,"retweet":23,"twit":"https://twitter.com/shimakazi/status/1074852255692599296","create_at":"2018-12-18T02:22:02Z","profile_image":"http://pbs.twimg.com/profile_images/1047062407930109952/aDHSTox6_normal.jpg","image_urls":["http://pbs.twimg.com/media/DuqkbLBUUAA8LcR.jpg"],"videos":[{"aspect_ratio":[0,0],"duration_millis":0,"variants":null}],"urls":null},{"url":"http://pbs.twimg.com/media/Duqf3nzUUAAvmVn.jpg","count":1,"longCount":1,"retweet":22,"twit":"https://twitter.com/natalie_mu/status/1074847240752062464","create_at":"2018-12-18T02:02:06Z","profile_image":"http://pbs.twimg.com/profile_images/541889848726921216/idvp5jki_normal.png","image_urls":["http://pbs.twimg.com/media/Duqf3nzUUAAvmVn.jpg"],"videos":[{"aspect_ratio":[0,0],"duration_millis":0,"variants":null}],"urls":["https://natalie.mu/music/news/312640"]},{"url":"","count":1,"longCount":1,"retweet":21,"twit":"https://twitter.com/ona_monkey_1/status/1074851313685413889","create_at":"2018-12-18T02:18:17Z","profile_image":"http://pbs.twimg.com/profile_images/1072884426344787968/KN0uLNuT_normal.jpg","image_urls":null,"videos":null,"urls":["https://twitter.com/i/web/status/1074851313685413889"]},{"url":"","count":1,"longCount":1,"retweet":21,"twit":"https://twitter.com/MEGAMIDEVICE/status/1074857698502402048","create_at":"2018-12-18T02:43:39Z","profile_image":"http://pbs.twimg.com/profile_images/1070502302526492672/JyiGnKxO_normal.jpg","image_urls":null,"videos":null,"urls":["https://www.kotobukiya.co.jp/megami-blog/megami-blog-164408/"]},{"url":"","count":1,"longCount":1,"retweet":20,"twit":"https://twitter.com/lea_tokyo/status/1074854854554738688","create_at":"2018-12-18T02:32:21Z","profile_image":"http://pbs.twimg.com/profile_images/1070670429910519813/jSNct8cP_normal.jpg","image_urls":null,"videos":null,"urls":["https://twitter.com/i/web/status/1074854854554738688"]},{"url":"","count":1,"longCount":1,"retweet":20,"twit":"https://twitter.com/takinamiyukari/status/1074852501013164032","create_at":"2018-12-18T02:23:00Z","profile_image":"http://pbs.twimg.com/profile_images/1040807748072398849/NK7wfc00_normal.jpg","image_urls":null,"videos":null,"urls":["https://ten-navi.com/dybe/3396/"]},{"url":"http://pbs.twimg.com/media/DuqlyJWUUAAu6f2.jpg","count":2,"longCount":2,"retweet":20,"twit":"https://twitter.com/_K_w_a_n_/status/1074853751481978880","create_at":"2018-12-18T02:27:58Z","profile_image":"http://pbs.twimg.com/profile_images/924780788335312896/yd86MVJZ_normal.jpg","image_urls":["http://pbs.twimg.com/media/DuqlyJWUUAAu6f2.jpg","http://pbs.twimg.com/media/DuqlyJWUUAI-e2c.jpg","http://pbs.twimg.com/media/DuqlyJWUwAAja5m.jpg","http://pbs.twimg.com/media/DuqlyJWV4AEs815.jpg"],"videos":[{"aspect_ratio":[0,0],"duration_millis":0,"variants":null},{"aspect_ratio":[0,0],"duration_millis":0,"variants":null},{"aspect_ratio":[0,0],"duration_millis":0,"variants":null},{"aspect_ratio":[0,0],"duration_millis":0,"variants":null}],"urls":null},{"url":"http://pbs.twimg.com/ext_tw_video_thumb/1074847988323778560/pu/img/0QsjW0iEmJdZ8aGe.jpg","count":1,"longCount":1,"retweet":19,"twit":"https://twitter.com/TWI_on_c/status/1074848082913677312","create_at":"2018-12-18T02:05:27Z","profile_image":"http://pbs.twimg.com/profile_images/1071046743217717248/AvB6hiXu_normal.jpg","image_urls":["http://pbs.twimg.com/ext_tw_video_thumb/1074847988323778560/pu/img/0QsjW0iEmJdZ8aGe.jpg"],"videos":[{"aspect_ratio":[16,9],"duration_millis":32380,"variants":[{"content_type":"video/mp4","bitrate":832000,"url":"https://video.twimg.com/ext_tw_video/1074847988323778560/pu/vid/640x360/hfp0V91WmOlVx1Zc.mp4?tag=6"},{"content_type":"application/x-mpegURL","bitrate":0,"url":"https://video.twimg.com/ext_tw_video/1074847988323778560/pu/pl/rRFqpApd0N5XQCUl.m3u8?tag=6"},{"content_type":"video/mp4","bitrate":256000,"url":"https://video.twimg.com/ext_tw_video/1074847988323778560/pu/vid/320x180/SE58LsETi6TpGQM-.mp4?tag=6"}]}],"urls":null},{"url":"","count":1,"longCount":1,"retweet":19,"twit":"https://twitter.com/Unisonleague_JP/status/1074861811076382721","create_at":"2018-12-18T03:00:00Z","profile_image":"http://pbs.twimg.com/profile_images/1068388098835275778/G-VtIoPL_normal.jpg","image_urls":null,"videos":null,"urls":["https://twitter.com/i/web/status/1074861811076382721"]},{"url":"http://pbs.twimg.com/media/DuqkRYIU0AAXL2l.jpg","count":1,"longCount":1,"retweet":19,"twit":"https://twitter.com/xxhama2/status/1074852086863429632","create_at":"2018-12-18T02:21:21Z","profile_image":"http://pbs.twimg.com/profile_images/1011171146677420032/MVWywDxk_normal.jpg","image_urls":["http://pbs.twimg.com/media/DuqkRYIU0AAXL2l.jpg","http://pbs.twimg.com/media/DuqkRYJUcAAYR2K.jpg"],"videos":[{"aspect_ratio":[0,0],"duration_millis":0,"variants":null},{"aspect_ratio":[0,0],"duration_millis":0,"variants":null}],"urls":null},{"url":"http://pbs.twimg.com/media/Duqfvs7UwAAkKh5.jpg","count":1,"longCount":1,"retweet":19,"twit":"https://twitter.com/so___mari/status/1074847109554130944","create_at":"2018-12-18T02:01:35Z","profile_image":"http://pbs.twimg.com/profile_images/1073505745998569472/FnFark6s_normal.jpg","image_urls":["http://pbs.twimg.com/media/Duqfvs7UwAAkKh5.jpg","http://pbs.twimg.com/media/Duqfvs7V4AA9RzF.jpg"],"videos":[{"aspect_ratio":[0,0],"duration_millis":0,"variants":null},{"aspect_ratio":[0,0],"duration_millis":0,"variants":null}],"urls":null},{"url":"","count":1,"longCount":1,"retweet":19,"twit":"https://twitter.com/TossuiKUN/status/1074848442269270017","create_at":"2018-12-18T02:06:53Z","profile_image":"http://pbs.twimg.com/profile_images/1060961154011287553/fNdYR3JM_normal.jpg","image_urls":null,"videos":null,"urls":["https://twitter.com/hemp_m/status/1074840399338827776"]},{"url":"","count":1,"longCount":1,"retweet":18,"twit":"https://twitter.com/ven12665/status/1074850427294801920","create_at":"2018-12-18T02:14:46Z","profile_image":"http://pbs.twimg.com/profile_images/983158339797319680/UHsF7dDq_normal.jpg","image_urls":null,"videos":null,"urls":["https://www.nikkei.com/article/DGKKZO39064600X11C18A2TJ3000/"]},{"url":"","count":1,"longCount":1,"retweet":18,"twit":"https://twitter.com/bprecords_/status/1074856487623610368","create_at":"2018-12-18T02:38:51Z","profile_image":"http://pbs.twimg.com/profile_images/568416748756422656/Rggqt3TV_normal.jpeg","image_urls":null,"videos":null,"urls":["https://twitter.com/i/web/status/1074856487623610368"]},{"url":"http://pbs.twimg.com/media/DuqkjBIU8AAm_Wu.jpg","count":1,"longCount":1,"retweet":18,"twit":"https://twitter.com/koi_tsumi/status/1074852389545373697","create_at":"2018-12-18T02:22:34Z","profile_image":"http://pbs.twimg.com/profile_images/1058853490699554816/rWLwvp-O_normal.jpg","image_urls":["http://pbs.twimg.com/media/DuqkjBIU8AAm_Wu.jpg"],"videos":[{"aspect_ratio":[0,0],"duration_millis":0,"variants":null}],"urls":null},{"url":"","count":1,"longCount":1,"retweet":18,"twit":"https://twitter.com/Shionndokidoki/status/1074852936113639424","create_at":"2018-12-18T02:24:44Z","profile_image":"http://pbs.twimg.com/profile_images/1067871582352228353/yPIWRmN8_normal.jpg","image_urls":null,"videos":null,"urls":["http://nice-app.tokyo/vBMADg"]},{"url":"","count":1,"longCount":1,"retweet":18,"twit":"https://twitter.com/kanzen55/status/1074847345227923456","create_at":"2018-12-18T02:02:31Z","profile_image":"http://pbs.twimg.com/profile_images/1003451712965754881/p8Thg7Ci_normal.jpg","image_urls":null,"videos":null,"urls":["https://twitter.com/i/web/status/1074847345227923456"]},{"url":"http://pbs.twimg.com/media/Duqh65EU0AEpfHp.jpg","count":1,"longCount":1,"retweet":17,"twit":"https://twitter.com/coded4d9dc/status/1074849500856967168","create_at":"2018-12-18T02:11:05Z","profile_image":"http://pbs.twimg.com/profile_images/1010942634452398080/sqte4JVa_normal.jpg","image_urls":["http://pbs.twimg.com/media/Duqh65EU0AEpfHp.jpg","http://pbs.twimg.com/media/Duqh65DUcAArSJa.jpg","http://pbs.twimg.com/media/Duqh65BU8AANsIN.jpg","http://pbs.twimg.com/media/Duqh65FUcAIx43_.jpg"],"videos":[{"aspect_ratio":[0,0],"duration_millis":0,"variants":null},{"aspect_ratio":[0,0],"duration_millis":0,"variants":null},{"aspect_ratio":[0,0],"duration_millis":0,"variants":null},{"aspect_ratio":[0,0],"duration_millis":0,"variants":null}],"urls":null},{"url":"","count":1,"longCount":1,"retweet":17,"twit":"https://twitter.com/ona_monkey_1/status/1074850003523272704","create_at":"2018-12-18T02:13:05Z","profile_image":"http://pbs.twimg.com/profile_images/1072884426344787968/KN0uLNuT_normal.jpg","image_urls":null,"videos":null,"urls":["https://twitter.com/i/web/status/1074850003523272704"]},{"url":"http://pbs.twimg.com/media/DuqiHZmU0AAdR2-.jpg","count":1,"longCount":1,"retweet":17,"twit":"https://twitter.com/samako211/status/1074849727017934849","create_at":"2018-12-18T02:11:59Z","profile_image":"http://pbs.twimg.com/profile_images/996088048994607105/gSVEXLsZ_normal.jpg","image_urls":["http://pbs.twimg.com/media/DuqiHZmU0AAdR2-.jpg"],"videos":[{"aspect_ratio":[0,0],"duration_millis":0,"variants":null}],"urls":null},{"url":"http://pbs.twimg.com/media/DuqgQ4ZVAAA-sIv.jpg","count":1,"longCount":1,"retweet":17,"twit":"https://twitter.com/amaxamt/status/1074847729350668288","create_at":"2018-12-18T02:04:03Z","profile_image":"http://pbs.twimg.com/profile_images/1053198242618331136/KZQfca31_normal.png","image_urls":["http://pbs.twimg.com/media/DuqgQ4ZVAAA-sIv.jpg","http://pbs.twimg.com/media/DuqgQ4pVsAAPtMy.jpg"],"videos":[{"aspect_ratio":[0,0],"duration_millis":0,"variants":null},{"aspect_ratio":[0,0],"duration_millis":0,"variants":null}],"urls":null},{"url":"http://pbs.twimg.com/media/DuqoHVPUwAAL8eb.jpg","count":1,"longCount":1,"retweet":17,"twit":"https://twitter.com/OfficialLVLZ_JP/status/1074856314092826624","create_at":"2018-12-18T02:38:09Z","profile_image":"http://pbs.twimg.com/profile_images/1064786889490673665/rU958DSj_normal.jpg","image_urls":["http://pbs.twimg.com/media/DuqoHVPUwAAL8eb.jpg","http://pbs.twimg.com/media/DuqoHVRVsAA_aRp.jpg"],"videos":[{"aspect_ratio":[0,0],"duration_millis":0,"variants":null},{"aspect_ratio":[0,0],"duration_millis":0,"variants":null}],"urls":null},{"url":"","count":1,"longCount":1,"retweet":16,"twit":"https://twitter.com/toho_stage/status/1074856656008343553","create_at":"2018-12-18T02:39:31Z","profile_image":"http://pbs.twimg.com/profile_images/669046334771494912/e75wwN1u_normal.png","image_urls":null,"videos":null,"urls":["https://www.tohostage.com/onyourfeet/ticket.html"]},{"url":"","count":1,"longCount":1,"retweet":16,"twit":"https://twitter.com/humiya0219/status/1074851018024771584","create_at":"2018-12-18T02:17:07Z","profile_image":"http://pbs.twimg.com/profile_images/1014392911612411906/ETo8HlMu_normal.jpg","image_urls":null,"videos":null,"urls":["https://twitter.com/i/web/status/1074851018024771584"]},{"url":"","count":1,"longCount":1,"retweet":16,"twit":"https://twitter.com/popolo_azabudai/status/1074861049952649216","create_at":"2018-12-18T02:56:58Z","profile_image":"http://pbs.twimg.com/profile_images/1009379989777608709/0voMJpAa_normal.jpg","image_urls":null,"videos":null,"urls":["https://twitter.com/i/web/status/1074861049952649216"]},{"url":"http://pbs.twimg.com/media/DuqgdiYVYAETElp.jpg","count":1,"longCount":1,"retweet":16,"twit":"https://twitter.com/kinoko_paf/status/1074847900373372928","create_at":"2018-12-18T02:04:43Z","profile_image":"http://pbs.twimg.com/profile_images/918547122827309056/X0zaTqVp_normal.jpg","image_urls":["http://pbs.twimg.com/media/DuqgdiYVYAETElp.jpg","http://pbs.twimg.com/media/DuqgdiWV4AYfw8X.jpg"],"videos":[{"aspect_ratio":[0,0],"duration_millis":0,"variants":null},{"aspect_ratio":[0,0],"duration_millis":0,"variants":null}],"urls":null},{"url":"","count":1,"longCount":1,"retweet":16,"twit":"https://twitter.com/car_watch/status/1074854531031126016","create_at":"2018-12-18T02:31:04Z","profile_image":"http://pbs.twimg.com/profile_images/785418072/caw_normal.gif","image_urls":null,"videos":null,"urls":["https://car.watch.impress.co.jp/docs/news/1158512.html"]},{"url":"","count":1,"longCount":1,"retweet":15,"twit":"https://twitter.com/livedoornews/status/1074851744943751168","create_at":"2018-12-18T02:20:00Z","profile_image":"http://pbs.twimg.com/profile_images/875662964988166149/whdJTD2I_normal.jpg","image_urls":null,"videos":null,"urls":["http://news.livedoor.com/article/detail/15750444/","https://twitter.com/i/web/status/1074851744943751168"]},{"url":"http://pbs.twimg.com/media/DuqoFSWXgAEYGAE.jpg","count":1,"longCount":1,"retweet":15,"twit":"https://twitter.com/gizmodojapan/status/1074856271210274816","create_at":"2018-12-18T02:37:59Z","profile_image":"http://pbs.twimg.com/profile_images/875673298998149120/AxlPt750_normal.jpg","image_urls":["http://pbs.twimg.com/media/DuqoFSWXgAEYGAE.jpg"],"videos":[{"aspect_ratio":[0,0],"duration_millis":0,"variants":null}],"urls":["https://www.gizmodo.jp/2018/12/mkhd-smartphone-camera-test-2018.html?utm_source=twitter\u0026utm_medium=feed\u0026utm_campaign=f17a57566a4f20b16bbe56d6354d1e3b"]},{"url":"","count":1,"longCount":1,"retweet":15,"twit":"https://twitter.com/gn___maria/status/1074851967153786880","create_at":"2018-12-18T02:20:53Z","profile_image":"http://pbs.twimg.com/profile_images/1073752341839400960/HHO43Xuf_normal.jpg","image_urls":null,"videos":null,"urls":["https://toyota-team8.jp/news/sp/kanto/20181217-595248805741633.php","https://toyota-team8.jp/news/sp/list/20181217-814521085413132.php","https://twitter.com/i/web/status/1074851967153786880"]},{"url":"","count":1,"longCount":1,"retweet":15,"twit":"https://twitter.com/sasapanda04/status/1074850208549240832","create_at":"2018-12-18T02:13:54Z","profile_image":"http://pbs.twimg.com/profile_images/821330500975370241/9B7cUvRm_normal.jpg","image_urls":null,"videos":null,"urls":["https://twitter.com/i/web/status/1074850208549240832"]},{"url":"http://pbs.twimg.com/media/DuqkejrUcAE1ua-.jpg","count":1,"longCount":1,"retweet":14,"twit":"https://twitter.com/hopstep3/status/1074853057127575552","create_at":"2018-12-18T02:25:13Z","profile_image":"http://pbs.twimg.com/profile_images/848100806951751680/_Gisq_m5_normal.jpg","image_urls":["http://pbs.twimg.com/media/DuqkejrUcAE1ua-.jpg","http://pbs.twimg.com/media/DuqkftVU8AAAy5o.jpg"],"videos":[{"aspect_ratio":[0,0],"duration_millis":0,"variants":null},{"aspect_ratio":[0,0],"duration_millis":0,"variants":null}],"urls":["http://seiga.nicovideo.jp/comic/29306"]},{"url":"http://pbs.twimg.com/media/DuqneXaUwAAxEKU.jpg","count":1,"longCount":1,"retweet":14,"twit":"https://twitter.com/owarai_natalie/status/1074855603074326528","create_at":"2018-12-18T02:35:20Z","profile_image":"http://pbs.twimg.com/profile_images/541891106527379457/IztbfaBz_normal.png","image_urls":["http://pbs.twimg.com/media/DuqneXaUwAAxEKU.jpg"],"videos":[{"aspect_ratio":[0,0],"duration_millis":0,"variants":null}],"urls":["https://natalie.mu/owarai/news/312638"]},{"url":"","count":1,"longCount":1,"retweet":14,"twit":"https://twitter.com/nekojiimovie/status/1074848716438134784","create_at":"2018-12-18T02:07:58Z","profile_image":"http://pbs.twimg.com/profile_images/1021591413308370944/S3tb7qPE_normal.jpg","image_urls":null,"videos":null,"urls":["https://www.amazon.co.jp/dp/4040653718/","https://twitter.com/nekojiimovie/status/1074848422904000512/photo/1"]},{"url":"","count":1,"longCount":1,"retweet":14,"twit":"https://twitter.com/Kyungil_jpn/status/1074847679195144192","create_at":"2018-12-18T02:03:51Z","profile_image":"http://pbs.twimg.com/profile_images/1048135383614029824/qpI8jpBZ_normal.jpg","image_urls":null,"videos":null,"urls":["https://twitter.com/i/web/status/1074847679195144192"]},{"url":"","count":2,"longCount":2,"retweet":14,"twit":"https://twitter.com/Favorite_ikbkr/status/1074852372990447616","create_at":"2018-12-18T02:22:30Z","profile_image":"http://pbs.twimg.com/profile_images/716097309419810816/dR3phF-x_normal.jpg","image_urls":null,"videos":null,"urls":["https://twitter.com/i/web/status/1074852372990447616"]},{"url":"","count":1,"longCount":1,"retweet":14,"twit":"https://twitter.com/muro5genki/status/1074854006290141184","create_at":"2018-12-18T02:28:59Z","profile_image":"http://pbs.twimg.com/profile_images/899636355860373504/JPOdnFJA_normal.jpg","image_urls":null,"videos":null,"urls":["https://twitter.com/tokyonecro_sm/status/1074850528868237313"]},{"url":"http://pbs.twimg.com/media/DuqiSIpUwAE3Y8c.jpg","count":1,"longCount":1,"retweet":14,"twit":"https://twitter.com/terasakanaoki/status/1074849899122851840","create_at":"2018-12-18T02:12:40Z","profile_image":"http://pbs.twimg.com/profile_images/946038451446587392/xpMeaTF4_normal.jpg","image_urls":["http://pbs.twimg.com/media/DuqiSIpUwAE3Y8c.jpg"],"videos":[{"aspect_ratio":[0,0],"duration_millis":0,"variants":null}],"urls":["https://popleta.goo.ne.jp/movie/25837/?utm_content=19_01#"]},{"url":"","count":1,"longCount":1,"retweet":14,"twit":"https://twitter.com/HIZUMIYA_Shop/status/1074855683013599232","create_at":"2018-12-18T02:35:39Z","profile_image":"http://pbs.twimg.com/profile_images/502796631201153024/9z3mbZ3M_normal.jpeg","image_urls":null,"videos":null,"urls":["https://twitter.com/i/web/status/1074855683013599232"]},{"url":"","count":1,"longCount":1,"retweet":13,"twit":"https://twitter.com/hiroshima_pref/status/1074854292031504384","create_at":"2018-12-18T02:30:07Z","profile_image":"http://pbs.twimg.com/profile_images/755950936049061888/L33v0yqY_normal.jpg","image_urls":null,"videos":null,"urls":["https://twitter.com/i/web/status/1074854292031504384"]},{"url":"","count":1,"longCount":1,"retweet":13,"twit":"https://twitter.com/kzstation/status/1074851062857662464","create_at":"2018-12-18T02:17:17Z","profile_image":"http://pbs.twimg.com/profile_images/919011150230052864/FP7LhpdB_normal.jpg","image_urls":null,"videos":null,"urls":["https://twitter.com/i/web/status/1074851062857662464"]},{"url":"http://pbs.twimg.com/media/DuqmI56UUAANE2V.jpg","count":1,"longCount":1,"retweet":13,"twit":"https://twitter.com/nomizuiori/status/1074854135613206528","create_at":"2018-12-18T02:29:30Z","profile_image":"http://pbs.twimg.com/profile_images/1057652533382930432/iD3igBTD_normal.jpg","image_urls":["http://pbs.twimg.com/media/DuqmI56UUAANE2V.jpg"],"videos":[{"aspect_ratio":[0,0],"duration_millis":0,"variants":null}],"urls":null},{"url":"","count":1,"longCount":1,"retweet":12,"twit":"https://twitter.com/utautaowow/status/1074853777906245637","create_at":"2018-12-18T02:28:05Z","profile_image":"http://pbs.twimg.com/profile_images/987952924952154112/SJfazvIg_normal.jpg","image_urls":null,"videos":null,"urls":["http://twieep.work/pOPEY7"]},{"url":"","count":1,"longCount":1,"retweet":12,"twit":"https://twitter.com/norigusuri/status/1074847367168475141","create_at":"2018-12-18T02:02:36Z","profile_image":"http://pbs.twimg.com/profile_images/978600348716736512/C5Qe8J3U_normal.jpg","image_urls":null,"videos":null,"urls":["https://twitter.com/i/web/status/1074847367168475141"]},{"url":"http://pbs.twimg.com/media/Duqi583U0AAyoc9.jpg","count":1,"longCount":1,"retweet":12,"twit":"https://twitter.com/iku_iku__/status/1074850585772314624","create_at":"2018-12-18T02:15:24Z","profile_image":"http://pbs.twimg.com/profile_images/977544046238248962/0agzxSdU_normal.jpg","image_urls":["http://pbs.twimg.com/media/Duqi583U0AAyoc9.jpg"],"videos":[{"aspect_ratio":[0,0],"duration_millis":0,"variants":null}],"urls":null},{"url":"","count":2,"longCount":2,"retweet":12,"twit":"https://twitter.com/iroduku_anime/status/1074856987983106048","create_at":"2018-12-18T02:40:50Z","profile_image":"http://pbs.twimg.com/profile_images/1027502348355039232/jHRJN886_normal.jpg","image_urls":null,"videos":null,"urls":["https://twitter.com/iroduku_anime/status/1071966458714845184"]},{"url":"","count":1,"longCount":1,"retweet":12,"twit":"https://twitter.com/DB30th/status/1074852855452819456","create_at":"2018-12-18T02:24:25Z","profile_image":"http://pbs.twimg.com/profile_images/980513263178850304/DHCDYvL8_normal.jpg","image_urls":null,"videos":null,"urls":["https://dragonball.news/news/n181217000.html"]},{"url":"http://pbs.twimg.com/media/DuqhpW5U8AAXWHJ.jpg","count":1,"longCount":1,"retweet":12,"twit":"https://twitter.com/medakanoyukie/status/1074851061637079040","create_at":"2018-12-18T02:17:17Z","profile_image":"http://pbs.twimg.com/profile_images/1062515497709723650/hDCM68ha_normal.jpg","image_urls":["http://pbs.twimg.com/media/DuqhpW5U8AAXWHJ.jpg"],"videos":[{"aspect_ratio":[0,0],"duration_millis":0,"variants":null}],"urls":null},{"url":"http://pbs.twimg.com/media/DuqotZcUcAAcMxA.jpg","count":1,"longCount":1,"retweet":12,"twit":"https://twitter.com/YoonJaeloveBAR/status/1074857018274410496","create_at":"2018-12-18T02:40:57Z","profile_image":"http://pbs.twimg.com/profile_images/1165715874/_____normal.jpg","image_urls":["http://pbs.twimg.com/media/DuqotZcUcAAcMxA.jpg","http://pbs.twimg.com/media/DuqotZaU0AAbfTf.jpg","http://pbs.twimg.com/media/DuqotZbVAAAD7Ph.jpg"],"videos":[{"aspect_ratio":[0,0],"duration_millis":0,"variants":null},{"aspect_ratio":[0,0],"duration_millis":0,"variants":null},{"aspect_ratio":[0,0],"duration_millis":0,"variants":null}],"urls":null},{"url":"","count":1,"longCount":1,"retweet":11,"twit":"https://twitter.com/niwatocosan/status/1074848044577746944","create_at":"2018-12-18T02:05:18Z","profile_image":"http://pbs.twimg.com/profile_images/1011965223073296385/b-oYjQNO_normal.jpg","image_urls":null,"videos":null,"urls":["https://twitter.com/i/web/status/1074848044577746944"]},{"url":"","count":1,"longCount":1,"retweet":11,"twit":"https://twitter.com/trg_happy/status/1074849610676416512","create_at":"2018-12-18T02:11:31Z","profile_image":"http://pbs.twimg.com/profile_images/875610200132038656/w8K-Cpks_normal.jpg","image_urls":null,"videos":null,"urls":["https://twitter.com/i/web/status/1074849610676416512"]},{"url":"","count":1,"longCount":1,"retweet":11,"twit":"https://twitter.com/ttensan/status/1074851493835026432","create_at":"2018-12-18T02:19:00Z","profile_image":"http://pbs.twimg.com/profile_images/539953792850997248/dauQjgSJ_normal.jpeg","image_urls":null,"videos":null,"urls":["https://ttensan.exblog.jp/27273716/"]},{"url":"","count":1,"longCount":1,"retweet":11,"twit":"https://twitter.com/ume_shirt/status/1074855967378923526","create_at":"2018-12-18T02:36:47Z","profile_image":"http://pbs.twimg.com/profile_images/1068259916500987904/eu9Z6_33_normal.jpg","image_urls":null,"videos":null,"urls":["https://twitter.com/i/web/status/1074855967378923526"]},{"url":"","count":1,"longCount":1,"retweet":11,"twit":"https://twitter.com/_nanashina_/status/1074849893594783744","create_at":"2018-12-18T02:12:39Z","profile_image":"http://pbs.twimg.com/profile_images/568432118141693952/eKWeGqzU_normal.jpeg","image_urls":null,"videos":null,"urls":["https://twitter.com/kotobukiya_2han/status/1074847034920714240"]},{"url":"http://pbs.twimg.com/media/Duqo9hlUYAAxTo3.jpg","count":1,"longCount":1,"retweet":11,"twit":"https://twitter.com/SF_Community/status/1074858090221060096","create_at":"2018-12-18T02:45:13Z","profile_image":"http://pbs.twimg.com/profile_images/1073918497212616704/K5Ewspr4_normal.jpg","image_urls":["http://pbs.twimg.com/media/Duqo9hlUYAAxTo3.jpg"],"videos":[{"aspect_ratio":[0,0],"duration_millis":0,"variants":null}],"urls":["https://www.evojapan.net/2019/"]},{"url":"","count":1,"longCount":1,"retweet":11,"twit":"https://twitter.com/now_adaruto/status/1074850501462654976","create_at":"2018-12-18T02:15:03Z","profile_image":"http://pbs.twimg.com/profile_images/1063329947010269190/tUito2ce_normal.jpg","image_urls":null,"videos":null,"urls":["http://smarte.work/NZuxAF"]},{"url":"","count":1,"longCount":1,"retweet":10,"twit":"https://twitter.com/adult_bari5/status/1074853783857856512","create_at":"2018-12-18T02:28:06Z","profile_image":"http://pbs.twimg.com/profile_images/980390197165772800/UunwCivU_normal.jpg","image_urls":null,"videos":null,"urls":["http://paripi.site/t8xoby"]},{"url":"","count":1,"longCount":1,"retweet":10,"twit":"https://twitter.com/errodouga2/status/1074852264760664064","create_at":"2018-12-18T02:22:04Z","profile_image":"http://pbs.twimg.com/profile_images/1074260949920505856/aBzoKNNk_normal.jpg","image_urls":null,"videos":null,"urls":["http://bdoy.site/pGDFS7"]},{"url":"","count":1,"longCount":1,"retweet":10,"twit":"https://twitter.com/motoofficial/status/1074847896787283973","create_at":"2018-12-18T02:04:42Z","profile_image":"http://pbs.twimg.com/profile_images/458955039503966208/gUjuGlsm_normal.png","image_urls":null,"videos":null,"urls":["https://twitter.com/motoofficial/status/1073915261294567425"]},{"url":"","count":1,"longCount":1,"retweet":10,"twit":"https://twitter.com/SNS_shuukyaku3/status/1074852032501112832","create_at":"2018-12-18T02:21:08Z","profile_image":"http://pbs.twimg.com/profile_images/1047657341179416576/Hwua-Fji_normal.jpg","image_urls":null,"videos":null,"urls":["http://twlk.xyz/vuy6UZ"]},{"url":"","count":1,"longCount":1,"retweet":10,"twit":"https://twitter.com/Trainfo_/status/1074855321842024448","create_at":"2018-12-18T02:34:13Z","profile_image":"http://pbs.twimg.com/profile_images/894528095167717382/Ep6P0-vj_normal.jpg","image_urls":null,"videos":null,"urls":["https://twitter.com/i/web/status/1074855321842024448"]},{"url":"","count":1,"longCount":1,"retweet":10,"twit":"https://twitter.com/tudukimi/status/1074857932364296193","create_at":"2018-12-18T02:44:35Z","profile_image":"http://pbs.twimg.com/profile_images/838593427432341507/G7bWNYex_normal.jpg","image_urls":null,"videos":null,"urls":["https://twitter.com/i/web/status/1074857932364296193"]},{"url":"http://pbs.twimg.com/media/DuqtI-qU0AAmOZ4.jpg","count":1,"longCount":1,"retweet":10,"twit":"https://twitter.com/Melody_Mariland/status/1074861833457098752","create_at":"2018-12-18T03:00:05Z","profile_image":"http://pbs.twimg.com/profile_images/980459809790046209/-Ofn7tE8_normal.jpg","image_urls":["http://pbs.twimg.com/media/DuqtI-qU0AAmOZ4.jpg"],"videos":[{"aspect_ratio":[0,0],"duration_millis":0,"variants":null}],"urls":null},{"url":"","count":1,"longCount":1,"retweet":10,"twit":"https://twitter.com/dwango_jp_PR/status/1074855410929086466","create_at":"2018-12-18T02:34:34Z","profile_image":"http://pbs.twimg.com/profile_images/876642324947755008/ISDE0syR_normal.jpg","image_urls":null,"videos":null,"urls":["https://twitter.com/i/web/status/1074855410929086466"]},{"url":"","count":1,"longCount":1,"retweet":9,"twit":"https://twitter.com/EB_RADIO/status/1074847986235011072","create_at":"2018-12-18T02:05:04Z","profile_image":"http://pbs.twimg.com/profile_images/937582958394740736/SrBPOUD9_normal.jpg","image_urls":null,"videos":null,"urls":["https://twitter.com/i/web/status/1074847986235011072"]},{"url":"http://pbs.twimg.com/media/Duqc840U0AEOAgx.jpg","count":1,"longCount":1,"retweet":9,"twit":"https://twitter.com/nijimen/status/1074854377460924416","create_at":"2018-12-18T02:30:28Z","profile_image":"http://pbs.twimg.com/profile_images/945519224667045888/Wusc5_Cm_normal.jpg","image_urls":["http://pbs.twimg.com/media/Duqc840U0AEOAgx.jpg","http://pbs.twimg.com/media/Duqc-5lUYAEbl4L.jpg","http://pbs.twimg.com/media/Duqc_OUUUAA8xrT.jpg","http://pbs.twimg.com/media/Duqc_wXVYAERlwM.jpg"],"videos":[{"aspect_ratio":[0,0],"duration_millis":0,"variants":null},{"aspect_ratio":[0,0],"duration_millis":0,"variants":null},{"aspect_ratio":[0,0],"duration_millis":0,"variants":null},{"aspect_ratio":[0,0],"duration_millis":0,"variants":null}],"urls":["https://nijimen.net/topics/20361"]},{"url":"","count":1,"longCount":1,"retweet":9,"twit":"https://twitter.com/ishiitakaaki/status/1074851815835848705","create_at":"2018-12-18T02:20:17Z","profile_image":"http://pbs.twimg.com/profile_images/1654603221/ishii_takaaki______normal.jpg","image_urls":null,"videos":null,"urls":["https://twitter.com/i/web/status/1074851815835848705"]},{"url":"http://pbs.twimg.com/media/DuqhcY2VsAArlzx.jpg","count":1,"longCount":1,"retweet":9,"twit":"https://twitter.com/kobeshinbun/status/1074849018801344512","create_at":"2018-12-18T02:09:10Z","profile_image":"http://pbs.twimg.com/profile_images/876044996369039360/nIQU518V_normal.jpg","image_urls":["http://pbs.twimg.com/media/DuqhcY2VsAArlzx.jpg"],"videos":[{"aspect_ratio":[0,0],"duration_millis":0,"variants":null}],"urls":["https://www.kobe-np.co.jp/news/jiken/201812/0011914221.shtml"]},{"url":"http://pbs.twimg.com/media/Duql1TFU8AAjd11.jpg","count":1,"longCount":1,"retweet":9,"twit":"https://twitter.com/korekore_chii/status/1074853801280983040","create_at":"2018-12-18T02:28:10Z","profile_image":"http://pbs.twimg.com/profile_images/1048932447272882176/IjmQZGb6_normal.jpg","image_urls":["http://pbs.twimg.com/media/Duql1TFU8AAjd11.jpg"],"videos":[{"aspect_ratio":[0,0],"duration_millis":0,"variants":null}],"urls":null},{"url":"","count":1,"longCount":1,"retweet":9,"twit":"https://twitter.com/dokoakuma/status/1074858047434981376","create_at":"2018-12-18T02:45:03Z","profile_image":"http://abs.twimg.com/sticky/default_profile_images/default_profile_normal.png","image_urls":null,"videos":null,"urls":["http://missile-news.site/H68JFT"]},{"url":"http://pbs.twimg.com/media/DuqqAnVVAAA7e-e.jpg","count":2,"longCount":2,"retweet":9,"twit":"https://twitter.com/JJENMAYER/status/1074858407490772992","create_at":"2018-12-18T02:46:28Z","profile_image":"http://pbs.twimg.com/profile_images/1074548461314297856/5SQj-akT_normal.jpg","image_urls":["http://pbs.twimg.com/media/DuqqAnVVAAA7e-e.jpg","http://pbs.twimg.com/media/DuqqApMUcAAUyi_.jpg"],"videos":[{"aspect_ratio":[0,0],"duration_millis":0,"variants":null},{"aspect_ratio":[0,0],"duration_millis":0,"variants":null}],"urls":null},{"url":"http://pbs.twimg.com/media/DuqkGHZU8AAkhfe.jpg","count":1,"longCount":1,"retweet":8,"twit":"https://twitter.com/katsudon_yoi/status/1074851900233678848","create_at":"2018-12-18T02:20:37Z","profile_image":"http://pbs.twimg.com/profile_images/1069762035200606208/iNqzhtWb_normal.jpg","image_urls":["http://pbs.twimg.com/media/DuqkGHZU8AAkhfe.jpg","http://pbs.twimg.com/media/DuqkGHXUwAA8BoL.jpg","http://pbs.twimg.com/media/DuqkGHZVsAAPhfJ.jpg","http://pbs.twimg.com/media/DuqkGHYUcAE2SE3.jpg"],"videos":[{"aspect_ratio":[0,0],"duration_millis":0,"variants":null},{"aspect_ratio":[0,0],"duration_millis":0,"variants":null},{"aspect_ratio":[0,0],"duration_millis":0,"variants":null},{"aspect_ratio":[0,0],"duration_millis":0,"variants":null}],"urls":null},{"url":"http://pbs.twimg.com/media/DuqjK9wUUAcwV1p.jpg","count":1,"longCount":1,"retweet":8,"twit":"https://twitter.com/mikoto111512/status/1074850899552481281","create_at":"2018-12-18T02:16:38Z","profile_image":"http://pbs.twimg.com/profile_images/1049645746859827200/I1R-HIUn_normal.jpg","image_urls":["http://pbs.twimg.com/media/DuqjK9wUUAcwV1p.jpg","http://pbs.twimg.com/media/DuqjK9wV4AIAFvg.jpg","http://pbs.twimg.com/media/DuqjK-RVYAEQXX9.jpg","http://pbs.twimg.com/media/DuqjK_FVAAAARTI.jpg"],"videos":[{"aspect_ratio":[0,0],"duration_millis":0,"variants":null},{"aspect_ratio":[0,0],"duration_millis":0,"variants":null},{"aspect_ratio":[0,0],"duration_millis":0,"variants":null},{"aspect_ratio":[0,0],"duration_millis":0,"variants":null}],"urls":null},{"url":"http://pbs.twimg.com/media/DuqjwFAXgAAKgzV.jpg","count":1,"longCount":1,"retweet":8,"twit":"https://twitter.com/sirase_bijyo/status/1074851524357033987","create_at":"2018-12-18T02:19:07Z","profile_image":"http://pbs.twimg.com/profile_images/1073065859436949504/bylk0Rpz_normal.jpg","image_urls":["http://pbs.twimg.com/media/DuqjwFAXgAAKgzV.jpg"],"videos":[{"aspect_ratio":[0,0],"duration_millis":0,"variants":null}],"urls":null},{"url":"","count":1,"longCount":1,"retweet":8,"twit":"https://twitter.com/imouto_maya_er/status/1074848992071172096","create_at":"2018-12-18T02:09:04Z","profile_image":"http://pbs.twimg.com/profile_images/1065619958527336448/Wm3v-6qu_normal.jpg","image_urls":null,"videos":null,"urls":["http://newss.work/2zRHrK"]},{"url":"http://pbs.twimg.com/media/DuqoxxwUYAA0GKV.jpg","count":1,"longCount":1,"retweet":8,"twit":"https://twitter.com/YoonJaeloveBAR/status/1074857054139904000","create_at":"2018-12-18T02:41:06Z","profile_image":"http://pbs.twimg.com/profile_images/1165715874/_____normal.jpg","image_urls":["http://pbs.twimg.com/media/DuqoxxwUYAA0GKV.jpg","http://pbs.twimg.com/media/DuqoxxxVYAAksEV.jpg","http://pbs.twimg.com/media/DuqoxxxV4AAFULX.jpg"],"videos":[{"aspect_ratio":[0,0],"duration_millis":0,"variants":null},{"aspect_ratio":[0,0],"duration_millis":0,"variants":null},{"aspect_ratio":[0,0],"duration_millis":0,"variants":null}],"urls":null},{"url":"","count":1,"longCount":1,"retweet":8,"twit":"https://twitter.com/tamiyainc/status/1074849971793350656","create_at":"2018-12-18T02:12:57Z","profile_image":"http://pbs.twimg.com/profile_images/2550787045/4qbszpeh9hx09fffygeo_normal.jpeg","image_urls":null,"videos":null,"urls":["https://www.tamiya.com/japan/event/tamiyaGP_20190120nissan"]},{"url":"","count":1,"longCount":1,"retweet":8,"twit":"https://twitter.com/Takamatti_iijan/status/1074847776377192448","create_at":"2018-12-18T02:04:14Z","profile_image":"http://pbs.twimg.com/profile_images/1065521119673765888/Mrruesgm_normal.jpg","image_urls":null,"videos":null,"urls":["https://twitter.com/i/web/status/1074847776377192448"]},{"url":"","count":1,"longCount":1,"retweet":8,"twit":"https://twitter.com/glutamine_music/status/1074852330435010560","create_at":"2018-12-18T02:22:20Z","profile_image":"http://pbs.twimg.com/profile_images/1010866337189543937/iixh0APx_normal.jpg","image_urls":null,"videos":null,"urls":["https://twitter.com/norigusuri/status/1074847367168475141"]},{"url":"","count":1,"longCount":1,"retweet":7,"twit":"https://twitter.com/Reuters_co_jp/status/1074849973500604416","create_at":"2018-12-18T02:12:58Z","profile_image":"http://pbs.twimg.com/profile_images/877357487099269120/Mxm5YvoG_normal.jpg","image_urls":null,"videos":null,"urls":["http://bit.ly/2CiKrxH"]},{"url":"","count":1,"longCount":1,"retweet":7,"twit":"https://twitter.com/aruru_Renai/status/1074856034236317696","create_at":"2018-12-18T02:37:03Z","profile_image":"http://pbs.twimg.com/profile_images/970249516942204928/bpCXHCsh_normal.jpg","image_urls":null,"videos":null,"urls":["http://twapp.xyz/jJZDT7"]},{"url":"http://pbs.twimg.com/media/Duqp8siUwAArIJ9.jpg","count":1,"longCount":1,"retweet":7,"twit":"https://twitter.com/phi496/status/1074858368106258432","create_at":"2018-12-18T02:46:19Z","profile_image":"http://pbs.twimg.com/profile_images/1072575367532154881/RHrSIXJt_normal.jpg","image_urls":["http://pbs.twimg.com/media/Duqp8siUwAArIJ9.jpg"],"videos":[{"aspect_ratio":[0,0],"duration_millis":0,"variants":null}],"urls":null},{"url":"http://pbs.twimg.com/media/DuqdFNeUcAA21WH.jpg","count":1,"longCount":1,"retweet":7,"twit":"https://twitter.com/shunkannews/status/1074847134237642752","create_at":"2018-12-18T02:01:41Z","profile_image":"http://pbs.twimg.com/profile_images/913214210003238914/hhyNvUSJ_normal.jpg","image_urls":["http://pbs.twimg.com/media/DuqdFNeUcAA21WH.jpg","http://pbs.twimg.com/media/DuqdLzuVsAA2lfQ.jpg","http://pbs.twimg.com/media/DuqdP7TUwAANx9A.jpg","http://pbs.twimg.com/media/DuqdSJ5VAAUYKoR.jpg"],"videos":[{"aspect_ratio":[0,0],"duration_millis":0,"variants":null},{"aspect_ratio":[0,0],"duration_millis":0,"variants":null},{"aspect_ratio":[0,0],"duration_millis":0,"variants":null},{"aspect_ratio":[0,0],"duration_millis":0,"variants":null}],"urls":["https://news.biglobe.ne.jp/entertainment/1218/blnews_181218_5328361866.html"]},{"url":"http://pbs.twimg.com/tweet_video_thumb/Duqg1ckUUAAXBJo.jpg","count":1,"longCount":1,"retweet":7,"twit":"https://twitter.com/kekekepopopo/status/1074848536691335168","create_at":"2018-12-18T02:07:15Z","profile_image":"http://pbs.twimg.com/profile_images/1069972177561243648/Cta1FJla_normal.jpg","image_urls":["http://pbs.twimg.com/tweet_video_thumb/Duqg1ckUUAAXBJo.jpg"],"videos":[{"aspect_ratio":[31,25],"duration_millis":0,"variants":[{"content_type":"video/mp4","bitrate":0,"url":"https://video.twimg.com/tweet_video/Duqg1ckUUAAXBJo.mp4"}]}],"urls":null},{"url":"","count":1,"longCount":1,"retweet":7,"twit":"https://twitter.com/xxkoh20xx/status/1074853629847203840","create_at":"2018-12-18T02:27:29Z","profile_image":"http://pbs.twimg.com/profile_images/2227850770/RIMG1202_normal.JPG","image_urls":null,"videos":null,"urls":["https://twitter.com/i/web/status/1074853629847203840"]},{"url":"http://pbs.twimg.com/media/Duqk1shU0AEV5we.jpg","count":1,"longCount":1,"retweet":7,"twit":"https://twitter.com/sagisagiz2/status/1074852712477409281","create_at":"2018-12-18T02:23:51Z","profile_image":"http://pbs.twimg.com/profile_images/961339604782608385/egvN3TVe_normal.jpg","image_urls":["http://pbs.twimg.com/media/Duqk1shU0AEV5we.jpg"],"videos":[{"aspect_ratio":[0,0],"duration_millis":0,"variants":null}],"urls":null},{"url":"http://pbs.twimg.com/media/DuqgwukVYAAhrLl.jpg","count":2,"longCount":2,"retweet":7,"twit":"https://twitter.com/sumi_r54/status/1074848227512336384","create_at":"2018-12-18T02:06:01Z","profile_image":"http://pbs.twimg.com/profile_images/1025707394565693441/B7ndCszi_normal.jpg","image_urls":["http://pbs.twimg.com/media/DuqgwukVYAAhrLl.jpg"],"videos":[{"aspect_ratio":[0,0],"duration_millis":0,"variants":null}],"urls":null},{"url":"","count":1,"longCount":1,"retweet":7,"twit":"https://twitter.com/kei_fukuchi/status/1074849346724614146","create_at":"2018-12-18T02:10:28Z","profile_image":"http://pbs.twimg.com/profile_images/1070217762226597888/OC9JEOJd_normal.jpg","image_urls":null,"videos":null,"urls":["https://withnews.jp/article/f0181217000qq000000000000000G00110701qq000018487A"]},{"url":"","count":1,"longCount":1,"retweet":7,"twit":"https://twitter.com/Funky_Heart/status/1074851109603139585","create_at":"2018-12-18T02:17:28Z","profile_image":"http://pbs.twimg.com/profile_images/378800000565191335/8574a7856ca2a79d33d549e4051bb8e1_normal.jpeg","image_urls":null,"videos":null,"urls":["https://twitter.com/i/web/status/1074851109603139585"]},{"url":"","count":1,"longCount":1,"retweet":7,"twit":"https://twitter.com/gekipia/status/1074858902750093312","create_at":"2018-12-18T02:48:26Z","profile_image":"http://pbs.twimg.com/profile_images/875532476734623744/do_fBESj_normal.jpg","image_urls":null,"videos":null,"urls":["https://twitter.com/i/web/status/1074858902750093312"]},{"url":"","count":1,"longCount":1,"retweet":7,"twit":"https://twitter.com/NiaghoCat/status/1074848669583564802","create_at":"2018-12-18T02:07:47Z","profile_image":"http://pbs.twimg.com/profile_images/1068466242581712896/SoIm4yho_normal.jpg","image_urls":null,"videos":null,"urls":["https://www.youtube.com/watch?v=RdjiKb5t4_c\u0026feature=youtu.be"]},{"url":"http://pbs.twimg.com/tweet_video_thumb/DuqoJ9UVsAAfZZ4.jpg","count":1,"longCount":1,"retweet":6,"twit":"https://twitter.com/to_to2ni/status/1074856412121976832","create_at":"2018-12-18T02:38:33Z","profile_image":"http://pbs.twimg.com/profile_images/952358005009367040/92fCT3N1_normal.jpg","image_urls":["http://pbs.twimg.com/tweet_video_thumb/DuqoJ9UVsAAfZZ4.jpg"],"videos":[{"aspect_ratio":[1,1],"duration_millis":0,"variants":[{"content_type":"video/mp4","bitrate":0,"url":"https://video.twimg.com/tweet_video/DuqoJ9UVsAAfZZ4.mp4"}]}],"urls":null},{"url":"","count":1,"longCount":1,"retweet":6,"twit":"https://twitter.com/dot_asahi_pub/status/1074855784666652672","create_at":"2018-12-18T02:36:03Z","profile_image":"http://pbs.twimg.com/profile_images/875538148180213760/QWf8MamD_normal.jpg","image_urls":null,"videos":null,"urls":["https://dot.asahi.com/aera/2018121700059.html?utm_source=dlvr.it\u0026utm_medium=social"]},{"url":"","count":1,"longCount":1,"retweet":6,"twit":"https://twitter.com/sakura_724s/status/1074851087377563648","create_at":"2018-12-18T02:17:23Z","profile_image":"http://pbs.twimg.com/profile_images/1062392825646465024/AvGULDDl_normal.jpg","image_urls":null,"videos":null,"urls":["https://twitter.com/i/web/status/1074851087377563648"]},{"url":"","count":1,"longCount":1,"retweet":6,"twit":"https://twitter.com/tss_tv_official/status/1074852721461649408","create_at":"2018-12-18T02:23:53Z","profile_image":"http://pbs.twimg.com/profile_images/1014442748638707713/rfuLlAXp_normal.jpg","image_urls":null,"videos":null,"urls":["https://twitter.com/i/web/status/1074852721461649408"]},{"url":"http://pbs.twimg.com/media/DuqgcZ4V4AAUdpP.jpg","count":1,"longCount":1,"retweet":6,"twit":"https://twitter.com/happyhappy51244/status/1074847951405510656","create_at":"2018-12-18T02:04:55Z","profile_image":"http://pbs.twimg.com/profile_images/730403388349808640/jbUiTEmJ_normal.jpg","image_urls":["http://pbs.twimg.com/media/DuqgcZ4V4AAUdpP.jpg","http://pbs.twimg.com/media/DuqgdY6VAAA6SIN.jpg","http://pbs.twimg.com/media/DuqgemIUwAAVdXL.jpg","http://pbs.twimg.com/media/DuqgfuoUwAEAs-g.jpg"],"videos":[{"aspect_ratio":[0,0],"duration_millis":0,"variants":null},{"aspect_ratio":[0,0],"duration_millis":0,"variants":null},{"aspect_ratio":[0,0],"duration_millis":0,"variants":null},{"aspect_ratio":[0,0],"duration_millis":0,"variants":null}],"urls":null},{"url":"http://pbs.twimg.com/media/Duqi7_rUYAMg8eY.jpg","count":1,"longCount":1,"retweet":6,"twit":"https://twitter.com/rgm79e/status/1074850654244331520","create_at":"2018-12-18T02:15:40Z","profile_image":"http://pbs.twimg.com/profile_images/1052925275745316864/MFSaOpvE_normal.jpg","image_urls":["http://pbs.twimg.com/media/Duqi7_rUYAMg8eY.jpg"],"videos":[{"aspect_ratio":[0,0],"duration_millis":0,"variants":null}],"urls":null},{"url":"http://pbs.twimg.com/media/Duqj_CjUYAESSZ5.jpg","count":1,"longCount":1,"retweet":6,"twit":"https://twitter.com/GenetPrabhakar2/status/1074851788971360256","create_at":"2018-12-18T02:20:10Z","profile_image":"http://pbs.twimg.com/profile_images/954410649068584960/sg86zJMT_normal.jpg","image_urls":["http://pbs.twimg.com/media/Duqj_CjUYAESSZ5.jpg"],"videos":[{"aspect_ratio":[0,0],"duration_millis":0,"variants":null}],"urls":["http://stageapi.site/YSVgS0"]},{"url":"","count":1,"longCount":1,"retweet":6,"twit":"https://twitter.com/shin34e/status/1074851116066791429","create_at":"2018-12-18T02:17:30Z","profile_image":"http://pbs.twimg.com/profile_images/1072139665262735360/WrIQpbf3_normal.jpg","image_urls":null,"videos":null,"urls":["http://mono-happy.xyz/b57FWr","https://twitter.com/i/web/status/1074851116066791429"]},{"url":"","count":1,"longCount":1,"retweet":6,"twit":"https://twitter.com/TOWER_Marubiru/status/1074848635404267521","create_at":"2018-12-18T02:07:39Z","profile_image":"http://pbs.twimg.com/profile_images/1065876785789718529/niyxdYUU_normal.jpg","image_urls":null,"videos":null,"urls":["https://tower.jp/store/news/2018/12/03806"]},{"url":"","count":1,"longCount":1,"retweet":6,"twit":"https://twitter.com/hyodo_masatoshi/status/1074858151264935936","create_at":"2018-12-18T02:45:27Z","profile_image":"http://pbs.twimg.com/profile_images/1542385249/88960001ok_normal.jpg","image_urls":null,"videos":null,"urls":["https://twitter.com/i/web/status/1074858151264935936"]},{"url":"http://pbs.twimg.com/media/DuqoTClU8AAbN4k.jpg","count":1,"longCount":1,"retweet":6,"twit":"https://twitter.com/kyoraku_tanu/status/1074856535463882752","create_at":"2018-12-18T02:39:02Z","profile_image":"http://pbs.twimg.com/profile_images/1068880463912042497/EK48buLR_normal.jpg","image_urls":["http://pbs.twimg.com/media/DuqoTClU8AAbN4k.jpg"],"videos":[{"aspect_ratio":[0,0],"duration_millis":0,"variants":null}],"urls":null},{"url":"","count":1,"longCount":1,"retweet":6,"twit":"https://twitter.com/i_lavKANKOKU_/status/1074847731921928192","create_at":"2018-12-18T02:04:03Z","profile_image":"http://pbs.twimg.com/profile_images/860910262794076161/igqdcsCl_normal.jpg","image_urls":null,"videos":null,"urls":["http://twi-me.top/yzn8xQ"]},{"url":"","count":1,"longCount":1,"retweet":6,"twit":"https://twitter.com/rosykiss_xxx/status/1074851541029253120","create_at":"2018-12-18T02:19:11Z","profile_image":"http://pbs.twimg.com/profile_images/1067306227208663040/neixVxp0_normal.jpg","image_urls":null,"videos":null,"urls":["https://twitter.com/i/web/status/1074851541029253120"]},{"url":"","count":1,"longCount":1,"retweet":6,"twit":"https://twitter.com/Favori_Rui/status/1074851311181414400","create_at":"2018-12-18T02:18:17Z","profile_image":"http://pbs.twimg.com/profile_images/1019801448932970496/MefaJLuO_normal.jpg","image_urls":null,"videos":null,"urls":["https://twitter.com/i/web/status/1074851311181414400"]},{"url":"http://pbs.twimg.com/media/Duql6SwUwAAligo.jpg","count":1,"longCount":1,"retweet":6,"twit":"https://twitter.com/miurano_hbg_sby/status/1074853888912646145","create_at":"2018-12-18T02:28:31Z","profile_image":"http://pbs.twimg.com/profile_images/856386056442085378/5r9NpyFF_normal.jpg","image_urls":["http://pbs.twimg.com/media/Duql6SwUwAAligo.jpg"],"videos":[{"aspect_ratio":[0,0],"duration_millis":0,"variants":null}],"urls":null},{"url":"","count":1,"longCount":1,"retweet":6,"twit":"https://twitter.com/cfm_update/status/1074847092168908808","create_at":"2018-12-18T02:01:31Z","profile_image":"http://pbs.twimg.com/profile_images/900893744454443008/4wG9XWBp_normal.jpg","image_urls":null,"videos":null,"urls":["https://ift.tt/2Log6kv"]},{"url":"","count":1,"longCount":1,"retweet":6,"twit":"https://twitter.com/hazuma/status/1074861054792876032","create_at":"2018-12-18T02:57:00Z","profile_image":"http://pbs.twimg.com/profile_images/3381711564/5843b8e273ea640628a8fecac2a5b349_normal.jpeg","image_urls":null,"videos":null,"urls":["https://twitter.com/i/web/status/1074861054792876032"]}],"urlRanking":null,"trends":[{"trends":[{"name":"#","url":"http://twitter.com/search?q=%23%E3%83%9D%E3%83%97%E3%83%AC%E3%82%BF","promoted_content":"","query":"%23%E3%83%9D%E3%83%97%E3%83%AC%E3%82%BF","tweet_volume":0},{"name":"","url":"http://twitter.com/search?q=%E3%82%AB%E3%83%96%E3%83%88%E3%83%9C%E3%83%BC%E3%82%B0","promoted_content":"","query":"%E3%82%AB%E3%83%96%E3%83%88%E3%83%9C%E3%83%BC%E3%82%B0","tweet_volume":25233},{"name":"LOVOT","url":"http://twitter.com/search?q=LOVOT","promoted_content":"","query":"LOVOT","tweet_volume":0},{"name":"G7","url":"http://twitter.com/search?q=G7%E6%9C%80%E4%B8%8B%E4%BD%8D","promoted_content":"","query":"G7%E6%9C%80%E4%B8%8B%E4%BD%8D","tweet_volume":0},{"name":"#","url":"http://twitter.com/search?q=%23%E6%9D%B1%E4%BA%AC%E9%A7%85%E5%AE%8C%E6%88%90%E8%A8%98%E5%BF%B5%E6%97%A5","promoted_content":"","query":"%23%E6%9D%B1%E4%BA%AC%E9%A7%85%E5%AE%8C%E6%88%90%E8%A8%98%E5%BF%B5%E6%97%A5","tweet_volume":0},{"name":"","url":"http://twitter.com/search?q=%E3%82%A2%E3%83%BC%E3%82%AB%E3%83%BC%E3%82%B7%E3%83%A3","promoted_content":"","query":"%E3%82%A2%E3%83%BC%E3%82%AB%E3%83%BC%E3%82%B7%E3%83%A3","tweet_volume":26074},{"name":"","url":"http://twitter.com/search?q=%E8%A8%BC%E5%88%B8%E5%8C%96","promoted_content":"","query":"%E8%A8%BC%E5%88%B8%E5%8C%96","tweet_volume":0},{"name":"","url":"http://twitter.com/search?q=%E8%BE%BA%E9%87%8E%E5%8F%A4%E7%BD%B2%E5%90%8D","promoted_content":"","query":"%E8%BE%BA%E9%87%8E%E5%8F%A4%E7%BD%B2%E5%90%8D","tweet_volume":48037},{"name":"#","url":"http://twitter.com/search?q=%23%E3%81%82%E3%81%AA%E3%81%9F%E3%82%AF%E3%83%AA%E3%82%B9%E3%83%9E%E3%82%B9%E3%81%AF","promoted_content":"","query":"%23%E3%81%82%E3%81%AA%E3%81%9F%E3%82%AF%E3%83%AA%E3%82%B9%E3%83%9E%E3%82%B9%E3%81%AF","tweet_volume":0},{"name":"","url":"http://twitter.com/search?q=%E6%9C%9D%E6%97%A5%E4%B8%96%E8%AB%96%E8%AA%BF%E6%9F%BB","promoted_content":"","query":"%E6%9C%9D%E6%97%A5%E4%B8%96%E8%AB%96%E8%AA%BF%E6%9F%BB","tweet_volume":0},{"name":"","url":"http://twitter.com/search?q=%E4%BA%AC%E6%B5%9C%E6%9D%B1%E5%8C%97%E7%B7%9A","promoted_content":"","query":"%E4%BA%AC%E6%B5%9C%E6%9D%B1%E5%8C%97%E7%B7%9A","tweet_volume":0},{"name":"#ij954","url":"http://twitter.com/search?q=%23ij954","promoted_content":"","query":"%23ij954","tweet_volume":0},{"name":"","url":"http://twitter.com/search?q=%E7%BF%BC%E3%81%8F%E3%82%93","promoted_content":"","query":"%E7%BF%BC%E3%81%8F%E3%82%93","tweet_volume":0},{"name":"#fmarinos","url":"http://twitter.com/search?q=%23fmarinos","promoted_content":"","query":"%23fmarinos","tweet_volume":0},{"name":"","url":"http://twitter.com/search?q=%E3%81%93%E3%81%90%E3%81%BE%E3%81%AE%E3%82%B1%E3%83%BC%E3%82%AD%E5%B1%8B%E3%81%95%E3%82%93","promoted_content":"","query":"%E3%81%93%E3%81%90%E3%81%BE%E3%81%AE%E3%82%B1%E3%83%BC%E3%82%AD%E5%B1%8B%E3%81%95%E3%82%93","tweet_volume":0},{"name":"","url":"http://twitter.com/search?q=%E4%BB%95%E6%8E%9B%E3%81%91%E4%BA%BA","promoted_content":"","query":"%E4%BB%95%E6%8E%9B%E3%81%91%E4%BA%BA","tweet_volume":0},{"name":"","url":"http://twitter.com/search?q=%E6%98%8E%E6%99%BA%E5%B0%8F%E4%BA%94%E9%83%8E","promoted_content":"","query":"%E6%98%8E%E6%99%BA%E5%B0%8F%E4%BA%94%E9%83%8E","tweet_volume":0},{"name":"","url":"http://twitter.com/search?q=%E7%B7%8F%E5%B4%A9%E3%82%8C","promoted_content":"","query":"%E7%B7%8F%E5%B4%A9%E3%82%8C","tweet_volume":0},{"name":"","url":"http://twitter.com/search?q=%E3%82%B3%E3%83%9F%E3%83%A5%E7%97%87","promoted_content":"","query":"%E3%82%B3%E3%83%9F%E3%83%A5%E7%97%87","tweet_volume":0},{"name":"","url":"http://twitter.com/search?q=%E3%83%95%E3%83%A9%E3%83%9A%E3%83%81%E3%83%BC%E3%83%8E","promoted_content":"","query":"%E3%83%95%E3%83%A9%E3%83%9A%E3%83%81%E3%83%BC%E3%83%8E","tweet_volume":0},{"name":"","url":"http://twitter.com/search?q=%E5%9B%BD%E9%80%A3%E7%B7%8F%E4%BC%9A","promoted_content":"","query":"%E5%9B%BD%E9%80%A3%E7%B7%8F%E4%BC%9A","tweet_volume":0},{"name":"3","url":"http://twitter.com/search?q=%E4%B8%AD3%E5%A5%B3%E5%AD%90%E9%80%AE%E6%8D%95","promoted_content":"","query":"%E4%B8%AD3%E5%A5%B3%E5%AD%90%E9%80%AE%E6%8D%95","tweet_volume":0},{"name":"","url":"http://twitter.com/search?q=%E6%9D%B1%E5%A4%A7%E4%B8%80","promoted_content":"","query":"%E6%9D%B1%E5%A4%A7%E4%B8%80","tweet_volume":0},{"name":"","url":"http://twitter.com/search?q=%E9%A0%86%E5%A4%A9%E5%A0%82%E5%A4%A7","promoted_content":"","query":"%E9%A0%86%E5%A4%A9%E5%A0%82%E5%A4%A7","tweet_volume":0},{"name":"/","url":"http://twitter.com/search?q=%E3%82%B3%E3%83%A0%E3%83%8B%E3%82%B3%2F%E3%82%A2%E3%82%B2%E3%83%8F%E8%AA%BF%E3%81%B9","promoted_content":"","query":"%E3%82%B3%E3%83%A0%E3%83%8B%E3%82%B3%2F%E3%82%A2%E3%82%B2%E3%83%8F%E8%AA%BF%E3%81%B9","tweet_volume":0},{"name":"FOMC","url":"http://twitter.com/search?q=FOMC","promoted_content":"","query":"FOMC","tweet_volume":0},{"name":"","url":"http://twitter.com/search?q=%E4%BF%A1%E5%8F%B7%E3%83%88%E3%83%A9%E3%83%96%E3%83%AB","promoted_content":"","query":"%E4%BF%A1%E5%8F%B7%E3%83%88%E3%83%A9%E3%83%96%E3%83%AB","tweet_volume":0},{"name":"G","url":"http://twitter.com/search?q=G%E3%83%9A%E3%83%B3","promoted_content":"","query":"G%E3%83%9A%E3%83%B3","tweet_volume":0},{"name":"","url":"http://twitter.com/search?q=%E3%83%97%E3%83%AA%E3%83%B3%E3%83%88%E3%83%8D%E3%83%83%E3%83%88","promoted_content":"","query":"%E3%83%97%E3%83%AA%E3%83%B3%E3%83%88%E3%83%8D%E3%83%83%E3%83%88","tweet_volume":0},{"name":"","url":"http://twitter.com/search?q=%E3%83%A1%E3%82%A4%E9%A6%96%E7%9B%B8","promoted_content":"","query":"%E3%83%A1%E3%82%A4%E9%A6%96%E7%9B%B8","tweet_volume":0},{"name":"","url":"http://twitter.com/search?q=%E7%99%BE%E7%94%B0%E5%A4%8F%E8%8F%9C%E5%AD%90","promoted_content":"","query":"%E7%99%BE%E7%94%B0%E5%A4%8F%E8%8F%9C%E5%AD%90","tweet_volume":0},{"name":"","url":"http://twitter.com/search?q=%E9%87%91%E8%9E%8D%E5%BA%81","promoted_content":"","query":"%E9%87%91%E8%9E%8D%E5%BA%81","tweet_volume":0},{"name":"5","url":"http://twitter.com/search?q=%E5%85%A85%E8%A9%B1","promoted_content":"","query":"%E5%85%A85%E8%A9%B1","tweet_volume":0},{"name":"","url":"http://twitter.com/search?q=%E5%88%A9%E4%B8%8A%E3%81%92","promoted_content":"","query":"%E5%88%A9%E4%B8%8A%E3%81%92","tweet_volume":0},{"name":"","url":"http://twitter.com/search?q=%E5%9B%BD%E9%80%A3%E5%8A%A0%E7%9B%9F%E8%A8%98%E5%BF%B5%E6%97%A5","promoted_content":"","query":"%E5%9B%BD%E9%80%A3%E5%8A%A0%E7%9B%9F%E8%A8%98%E5%BF%B5%E6%97%A5","tweet_volume":0},{"name":"iOS 12.1.2","url":"http://twitter.com/search?q=%22iOS+12.1.2%22","promoted_content":"","query":"%22iOS+12.1.2%22","tweet_volume":0},{"name":"","url":"http://twitter.com/search?q=%E6%9C%AD%E5%B9%8C%E3%81%AE%E7%88%86%E7%99%BA%E3%83%93%E3%83%AB","promoted_content":"","query":"%E6%9C%AD%E5%B9%8C%E3%81%AE%E7%88%86%E7%99%BA%E3%83%93%E3%83%AB","tweet_volume":0},{"name":"#","url":"http://twitter.com/search?q=%23%E3%83%95%E3%83%A9%E3%82%B2%E6%97%A5","promoted_content":"","query":"%23%E3%83%95%E3%83%A9%E3%82%B2%E6%97%A5","tweet_volume":0},{"name":"#","url":"http://twitter.com/search?q=%23%E6%AD%A3%E7%9B%B4%E3%82%AC%E3%83%81%E6%81%8B%E3%83%81%E3%83%A3%E3%83%AC%E3%83%B3%E3%82%B8","promoted_content":"","query":"%23%E6%AD%A3%E7%9B%B4%E3%82%AC%E3%83%81%E6%81%8B%E3%83%81%E3%83%A3%E3%83%AC%E3%83%B3%E3%82%B8","tweet_volume":0},{"name":"#PANDORA_BOXXX","url":"http://twitter.com/search?q=%23PANDORA_BOXXX","promoted_content":"","query":"%23PANDORA_BOXXX","tweet_volume":0},{"name":"#T","url":"http://twitter.com/search?q=%23%E3%83%A4%E3%83%90%E3%82%A4T%E3%82%B7%E3%83%A3%E3%83%84%E5%B1%8B%E3%81%95%E3%82%93","promoted_content":"","query":"%23%E3%83%A4%E3%83%90%E3%82%A4T%E3%82%B7%E3%83%A3%E3%83%84%E5%B1%8B%E3%81%95%E3%82%93","tweet_volume":0}],"as_of":"2018-12-18T03:01:23Z","created_at":"2018-12-18T02:55:23Z","locations":[{"name":"Japan","woeid":23424856}]}]}